{"resultSet":{"vehicle":[{"tripID":4411642,"serviceDate":1395644400000,"direction":1,"garage":"CENTER","type":"bus","lastLocID":1831,"messageCode":268,"time":1395734432766,"expires":1395734852000,"signMessageLong":"14  Hawthorne to Portland","extraBlockID":null,"locationInScheduleDay":90032,"longitude":-122.5662917,"blockID":1406,"offRoute":false,"nextLocID":13236,"vehicleID":3128,"signMessage":"14 To Portland","extraTripID":null,"nextStopSeq":2,"routeNumber":14,"vehicleLoad":"unknown","bearing":291,"lastStopSeq":1,"inCongestion":false,"delay":0,"latitude":45.4791765},{"tripID":4417968,"serviceDate":1395644400000,"direction":0,"garage":"POWELL","type":"bus","lastLocID":3170,"messageCode":766,"time":1395734421201,"expires":1395734837000,"signMessageLong":"72  Killingsworth/82nd to Swan Island-Anchor St","extraBlockID":null,"locationInScheduleDay":89862,"longitude":-122.6831672,"blockID":7251,"offRoute":false,"nextLocID":3159,"vehicleID":2545,"signMessage":"72 Swan Island","extraTripID":null,"nextStopSeq":100,"routeNumber":72,"vehicleLoad":"unknown","bearing":270,"lastStopSeq":99,"inCongestion":false,"delay":-155,"latitude":45.5626643},{"tripID":4411387,"serviceDate":1395644400000,"direction":0,"garage":"CENTER","type":"bus","lastLocID":8134,"messageCode":266,"time":1395734432764,"expires":1395734852000,"signMessageLong":"14  Hawthorne to 94th & Foster","extraBlockID":null,"locationInScheduleDay":89987,"longitude":-122.5654093,"blockID":1403,"offRoute":false,"nextLocID":1831,"vehicleID":2625,"signMessage":"14 To 94-Foster","extraTripID":null,"nextStopSeq":49,"routeNumber":14,"vehicleLoad":"unknown","bearing":291,"lastStopSeq":48,"inCongestion":false,"delay":-45,"latitude":45.4789373},{"tripID":4418297,"serviceDate":1395644400000,"direction":1,"garage":"POWELL","type":"bus","lastLocID":7961,"messageCode":760,"time":1395734419857,"expires":1395734837000,"signMessageLong":"72  Killingsworth/82nd to Clackamas TC","extraBlockID":null,"locationInScheduleDay":90052,"longitude":-122.5790921,"blockID":7253,"offRoute":false,"nextLocID":7950,"vehicleID":3019,"signMessage":"72 Clackamas TC","extraTripID":null,"nextStopSeq":95,"routeNumber":72,"vehicleLoad":"unknown","bearing":180,"lastStopSeq":94,"inCongestion":false,"delay":35,"latitude":45.474184},{"tripID":4418298,"serviceDate":1395644400000,"direction":1,"garage":"POWELL","type":"bus","lastLocID":3190,"messageCode":760,"time":1395734435781,"expires":1395734855000,"signMessageLong":"72  Killingsworth/82nd to Clackamas TC","extraBlockID":null,"locationInScheduleDay":90034,"longitude":-122.6305173,"blockID":7236,"offRoute":false,"nextLocID":3191,"vehicleID":3022,"signMessage":"72 Clackamas TC","extraTripID":null,"nextStopSeq":36,"routeNumber":72,"vehicleLoad":"unknown","bearing":89,"lastStopSeq":35,"inCongestion":false,"delay":-1,"latitude":45.5627236},{"tripID":4417969,"serviceDate":1395644400000,"direction":0,"garage":"POWELL","type":"bus","lastLocID":8010,"messageCode":766,"time":1395734421149,"expires":1395734838000,"signMessageLong":"72  Killingsworth/82nd to Swan Island-Anchor St","extraBlockID":null,"locationInScheduleDay":90118,"longitude":-122.5789622,"blockID":7238,"offRoute":false,"nextLocID":7999,"vehicleID":3035,"signMessage":"72 Swan Island","extraTripID":null,"nextStopSeq":48,"routeNumber":72,"vehicleLoad":"unknown","bearing":0,"lastStopSeq":47,"inCongestion":false,"delay":100,"latitude":45.5335012}],"queryTime":1395734447664}}
