{"resultSet":{"vehicle":[{"tripID":4419101,"serviceDate":1395730800000,"direction":0,"garage":"POWELL","type":"bus","lastLocID":2383,"messageCode":809,"time":1395773360532,"expires":1395773778000,"signMessageLong":"77  Broadway/Halsey to Troutdale","extraBlockID":null,"locationInScheduleDay":42872,"longitude":-122.5156314,"blockID":7736,"offRoute":false,"nextLocID":2385,"vehicleID":2221,"signMessage":"77 To Troutdale","extraTripID":null,"nextStopSeq":69,"routeNumber":77,"vehicleLoad":"unknown","bearing":90,"lastStopSeq":68,"inCongestion":false,"delay":314,"latitude":45.5336881},{"tripID":4411590,"serviceDate":1395730800000,"direction":1,"garage":"POWELL","type":"bus","lastLocID":12948,"messageCode":268,"time":1395773363732,"expires":1395773781000,"signMessageLong":"14  Hawthorne to Portland","extraBlockID":null,"locationInScheduleDay":42526,"longitude":-122.5892441,"blockID":1438,"offRoute":false,"nextLocID":1811,"vehicleID":2220,"signMessage":"14 To Portland","extraTripID":null,"nextStopSeq":9,"routeNumber":14,"vehicleLoad":"unknown","bearing":298,"lastStopSeq":8,"inCongestion":false,"delay":-35,"latitude":45.4865378},{"tripID":4411332,"serviceDate":1395730800000,"direction":0,"garage":"POWELL","type":"bus","lastLocID":10196,"messageCode":266,"time":1395773360551,"expires":1395773778000,"signMessageLong":"14  Hawthorne to 94th & Foster","extraBlockID":null,"locationInScheduleDay":42597,"longitude":-122.5980356,"blockID":1440,"offRoute":false,"nextLocID":1802,"vehicleID":2265,"signMessage":"14 To 94-Foster","extraTripID":null,"nextStopSeq":35,"routeNumber":14,"vehicleLoad":"unknown","bearing":120,"lastStopSeq":34,"inCongestion":false,"delay":39,"latitude":45.4901778},{"tripID":4417899,"serviceDate":1395730800000,"direction":0,"garage":"POWELL","type":"bus","lastLocID":8015,"messageCode":766,"time":1395773375689,"expires":1395773792000,"signMessageLong":"72  Killingsworth/82nd to Swan Island-Anchor St","extraBlockID":null,"locationInScheduleDay":42608,"longitude":-122.5790762,"blockID":7247,"offRoute":false,"nextLocID":8017,"vehicleID":2250,"signMessage":"72 Swan Island","extraTripID":null,"nextStopSeq":8,"routeNumber":72,"vehicleLoad":"unknown","bearing":358,"lastStopSeq":7,"inCongestion":false,"delay":36,"latitude":45.4515258},{"tripID":4417897,"serviceDate":1395730800000,"direction":0,"garage":"POWELL","type":"bus","lastLocID":7928,"messageCode":766,"time":1395773375719,"expires":1395773792000,"signMessageLong":"72  Killingsworth/82nd to Swan Island-Anchor St","extraBlockID":null,"locationInScheduleDay":42568,"longitude":-122.5790443,"blockID":7246,"offRoute":false,"nextLocID":8047,"vehicleID":2296,"signMessage":"72 Swan Island","extraTripID":null,"nextStopSeq":40,"routeNumber":72,"vehicleLoad":"unknown","bearing":357,"lastStopSeq":39,"inCongestion":false,"delay":-4,"latitude":45.5182643},{"tripID":4418221,"serviceDate":1395730800000,"direction":1,"garage":"POWELL","type":"bus","lastLocID":8008,"messageCode":760,"time":1395773363822,"expires":1395773781000,"signMessageLong":"72  Killingsworth/82nd to Clackamas TC","extraBlockID":null,"locationInScheduleDay":42574,"longitude":-122.5786935,"blockID":7252,"offRoute":false,"nextLocID":7923,"vehicleID":2283,"signMessage":"72 Clackamas TC","extraTripID":null,"nextStopSeq":78,"routeNumber":72,"vehicleLoad":"unknown","bearing":180,"lastStopSeq":77,"inCongestion":false,"delay":13,"latitude":45.5082899},{"tripID":4418220,"serviceDate":1395730800000,"direction":1,"garage":"POWELL","type":"bus","lastLocID":7965,"messageCode":760,"time":1395773319046,"expires":1395773736000,"signMessageLong":"72  Killingsworth/82nd to Clackamas TC","extraBlockID":null,"locationInScheduleDay":42509,"longitude":-122.5789564,"blockID":7244,"offRoute":false,"nextLocID":8028,"vehicleID":2276,"signMessage":"72 Clackamas TC","extraTripID":null,"nextStopSeq":91,"routeNumber":72,"vehicleLoad":"unknown","bearing":181,"lastStopSeq":90,"inCongestion":false,"delay":-7,"latitude":45.4836186},{"tripID":4417334,"serviceDate":1395730800000,"direction":1,"garage":"CENTER","type":"bus","lastLocID":9368,"messageCode":788,"time":1395773375592,"expires":1395773793000,"signMessageLong":"70  12th/NE 33rd Ave to Milwaukie","extraBlockID":null,"locationInScheduleDay":42573,"longitude":-122.6357648,"blockID":7008,"offRoute":false,"nextLocID":9414,"vehicleID":2506,"signMessage":"70 To Milwaukie","extraTripID":null,"nextStopSeq":2,"routeNumber":70,"vehicleLoad":"unknown","bearing":180,"lastStopSeq":1,"inCongestion":false,"delay":0,"latitude":45.5898735},{"tripID":4413890,"serviceDate":1395730800000,"direction":1,"garage":"CENTER","type":"bus","lastLocID":2570,"messageCode":458,"time":1395773345386,"expires":1395773764000,"signMessageLong":"31  To Milwaukie","extraBlockID":null,"locationInScheduleDay":42624,"longitude":-122.6408726,"blockID":3102,"offRoute":false,"nextLocID":8225,"vehicleID":2526,"signMessage":"31 To Milwaukie","extraTripID":null,"nextStopSeq":24,"routeNumber":31,"vehicleLoad":"unknown","bearing":260,"lastStopSeq":23,"inCongestion":false,"delay":80,"latitude":45.4456188},{"tripID":4417896,"serviceDate":1395730800000,"direction":0,"garage":"POWELL","type":"bus","lastLocID":8026,"messageCode":766,"time":1395773342227,"expires":1395773762000,"signMessageLong":"72  Killingsworth/82nd to Swan Island-Anchor St","extraBlockID":null,"locationInScheduleDay":42663,"longitude":-122.5786287,"blockID":7238,"offRoute":false,"nextLocID":8063,"vehicleID":2527,"signMessage":"72 Swan Island","extraTripID":null,"nextStopSeq":60,"routeNumber":72,"vehicleLoad":"unknown","bearing":0,"lastStopSeq":59,"inCongestion":false,"delay":121,"latitude":45.5555842},{"tripID":4417182,"serviceDate":1395730800000,"direction":0,"garage":"CENTER","type":"bus","lastLocID":13477,"messageCode":781,"time":1395773375657,"expires":1395773792000,"signMessageLong":"70  12th/NE 33rd Ave to NE Sunderland via 17th & Tacoma","extraBlockID":null,"locationInScheduleDay":42572,"longitude":-122.6407309,"blockID":7002,"offRoute":false,"nextLocID":8225,"vehicleID":2524,"signMessage":"70 To Sunderland via 17th","extraTripID":null,"nextStopSeq":2,"routeNumber":70,"vehicleLoad":"unknown","bearing":81,"lastStopSeq":1,"inCongestion":false,"delay":0,"latitude":45.4448667},{"tripID":4418224,"serviceDate":1395730800000,"direction":1,"garage":"POWELL","type":"bus","lastLocID":5927,"messageCode":760,"time":1395773378415,"expires":1395773796000,"signMessageLong":"72  Killingsworth/82nd to Clackamas TC","extraBlockID":null,"locationInScheduleDay":42605,"longitude":-122.6615199,"blockID":7239,"offRoute":false,"nextLocID":46,"vehicleID":2540,"signMessage":"72 Clackamas TC","extraTripID":null,"nextStopSeq":21,"routeNumber":72,"vehicleLoad":"unknown","bearing":180,"lastStopSeq":20,"inCongestion":false,"delay":29,"latitude":45.5617436},{"tripID":4417898,"serviceDate":1395730800000,"direction":0,"garage":"POWELL","type":"bus","lastLocID":8040,"messageCode":766,"time":1395773366391,"expires":1395773783000,"signMessageLong":"72  Killingsworth/82nd to Swan Island-Anchor St","extraBlockID":null,"locationInScheduleDay":42602,"longitude":-122.5788602,"blockID":7240,"offRoute":false,"nextLocID":7984,"vehicleID":2533,"signMessage":"72 Swan Island","extraTripID":null,"nextStopSeq":25,"routeNumber":72,"vehicleLoad":"unknown","bearing":1,"lastStopSeq":24,"inCongestion":false,"delay":39,"latitude":45.4881914},{"tripID":4417895,"serviceDate":1395730800000,"direction":0,"garage":"POWELL","type":"bus","lastLocID":3200,"messageCode":766,"time":1395773378635,"expires":1395773797000,"signMessageLong":"72  Killingsworth/82nd to Swan Island-Anchor St","extraBlockID":null,"locationInScheduleDay":42447,"longitude":-122.6197033,"blockID":7236,"offRoute":false,"nextLocID":3197,"vehicleID":2552,"signMessage":"72 Swan Island","extraTripID":null,"nextStopSeq":75,"routeNumber":72,"vehicleLoad":"unknown","bearing":270,"lastStopSeq":74,"inCongestion":false,"delay":-130,"latitude":45.5628098},{"tripID":4418219,"serviceDate":1395730800000,"direction":1,"garage":"POWELL","type":"bus","lastLocID":7945,"messageCode":760,"time":1395773360634,"expires":1395773779000,"signMessageLong":"72  Killingsworth/82nd to Clackamas TC","extraBlockID":null,"locationInScheduleDay":42197,"longitude":-122.5790534,"blockID":7242,"offRoute":false,"nextLocID":7952,"vehicleID":2548,"signMessage":"72 Clackamas TC","extraTripID":null,"nextStopSeq":101,"routeNumber":72,"vehicleLoad":"unknown","bearing":180,"lastStopSeq":100,"inCongestion":false,"delay":-362,"latitude":45.4614252},{"tripID":4417894,"serviceDate":1395730800000,"direction":0,"garage":"POWELL","type":"bus","lastLocID":10184,"messageCode":766,"time":1395773387364,"expires":1395773806000,"signMessageLong":"72  Killingsworth/82nd to Swan Island-Anchor St","extraBlockID":null,"locationInScheduleDay":42407,"longitude":-122.661265,"blockID":7253,"offRoute":false,"nextLocID":5890,"vehicleID":2318,"signMessage":"72 Swan Island","extraTripID":null,"nextStopSeq":92,"routeNumber":72,"vehicleLoad":"unknown","bearing":270,"lastStopSeq":91,"inCongestion":false,"delay":-179,"latitude":45.5591227},{"tripID":4411333,"serviceDate":1395730800000,"direction":0,"garage":"POWELL","type":"bus","lastLocID":2617,"messageCode":266,"time":1395773381762,"expires":1395773798000,"signMessageLong":"14  Hawthorne to 94th & Foster","extraBlockID":null,"locationInScheduleDay":42658,"longitude":-122.6300255,"blockID":1435,"offRoute":false,"nextLocID":2620,"vehicleID":2316,"signMessage":"14 To 94-Foster","extraTripID":null,"nextStopSeq":16,"routeNumber":14,"vehicleLoad":"unknown","bearing":90,"lastStopSeq":15,"inCongestion":false,"delay":80,"latitude":45.5120595},{"tripID":4419240,"serviceDate":1395730800000,"direction":1,"garage":"CENTER","type":"bus","lastLocID":2392,"messageCode":813,"time":1395773348602,"expires":1395773767000,"signMessageLong":"77  Broadway/Halsey to Montgomery Park","extraBlockID":null,"locationInScheduleDay":42505,"longitude":-122.5009137,"blockID":7705,"offRoute":false,"nextLocID":2390,"vehicleID":2720,"signMessage":"77 Montgomry Pk","extraTripID":null,"nextStopSeq":29,"routeNumber":77,"vehicleLoad":"unknown","bearing":269,"lastStopSeq":28,"inCongestion":false,"delay":-42,"latitude":45.5336651},{"tripID":4411588,"serviceDate":1395730800000,"direction":1,"garage":"CENTER","type":"bus","lastLocID":3641,"messageCode":268,"time":1395773360517,"expires":1395773780000,"signMessageLong":"14  Hawthorne to Portland","extraBlockID":null,"locationInScheduleDay":42245,"longitude":-122.6584655,"blockID":1404,"offRoute":false,"nextLocID":3633,"vehicleID":2718,"signMessage":"14 To Portland","extraTripID":null,"nextStopSeq":41,"routeNumber":14,"vehicleLoad":"unknown","bearing":270,"lastStopSeq":40,"inCongestion":false,"delay":-315,"latitude":45.5129222},{"tripID":4417181,"serviceDate":1395730800000,"direction":0,"garage":"CENTER","type":"bus","lastLocID":4539,"messageCode":780,"time":1395773381664,"expires":1395773798000,"signMessageLong":"70  12th/NE 33rd Ave to NE Sunderland","extraBlockID":null,"locationInScheduleDay":42554,"longitude":-122.6542075,"blockID":7007,"offRoute":false,"nextLocID":6578,"vehicleID":2709,"signMessage":"70 To Sunderlnd","extraTripID":null,"nextStopSeq":27,"routeNumber":70,"vehicleLoad":"unknown","bearing":29,"lastStopSeq":26,"inCongestion":false,"delay":-24,"latitude":45.5028135},{"tripID":4417332,"serviceDate":1395730800000,"direction":1,"garage":"CENTER","type":"bus","lastLocID":6554,"messageCode":790,"time":1395773375591,"expires":1395773792000,"signMessageLong":"70  12th Ave to Milwaukie via 13th & Tacoma","extraBlockID":null,"locationInScheduleDay":42649,"longitude":-122.6546631,"blockID":7001,"offRoute":false,"nextLocID":6542,"vehicleID":2704,"signMessage":"70 To Milw via 13","extraTripID":null,"nextStopSeq":50,"routeNumber":70,"vehicleLoad":"unknown","bearing":180,"lastStopSeq":49,"inCongestion":false,"delay":77,"latitude":45.5175357},{"tripID":4417335,"serviceDate":1395730800000,"direction":1,"garage":"CENTER","type":"bus","lastLocID":9368,"messageCode":788,"time":1395773372522,"expires":1395773791000,"signMessageLong":"70  12th/NE 33rd Ave to Milwaukie","extraBlockID":null,"locationInScheduleDay":42571,"longitude":-122.6357648,"blockID":7003,"offRoute":false,"nextLocID":9414,"vehicleID":2705,"signMessage":"70 To Milwaukie","extraTripID":null,"nextStopSeq":2,"routeNumber":70,"vehicleLoad":"unknown","bearing":180,"lastStopSeq":1,"inCongestion":false,"delay":0,"latitude":45.5898735},{"tripID":4417331,"serviceDate":1395730800000,"direction":1,"garage":"CENTER","type":"bus","lastLocID":6874,"messageCode":791,"time":1395773378388,"expires":1395773796000,"signMessageLong":"70  To Milwaukie","extraBlockID":null,"locationInScheduleDay":42551,"longitude":-122.6470584,"blockID":7004,"offRoute":false,"nextLocID":6896,"vehicleID":2701,"signMessage":"70 To Milwaukie","extraTripID":null,"nextStopSeq":72,"routeNumber":70,"vehicleLoad":"unknown","bearing":179,"lastStopSeq":71,"inCongestion":false,"delay":-25,"latitude":45.4669898},{"tripID":4419102,"serviceDate":1395730800000,"direction":0,"garage":"CENTER","type":"bus","lastLocID":6235,"messageCode":809,"time":1395773360607,"expires":1395773779000,"signMessageLong":"77  Broadway/Halsey to Troutdale","extraBlockID":null,"locationInScheduleDay":42627,"longitude":-122.6432507,"blockID":7704,"offRoute":false,"nextLocID":6237,"vehicleID":2614,"signMessage":"77 To Troutdale","extraTripID":null,"nextStopSeq":27,"routeNumber":77,"vehicleLoad":"unknown","bearing":90,"lastStopSeq":26,"inCongestion":false,"delay":68,"latitude":45.5343036},{"tripID":4411589,"serviceDate":1395730800000,"direction":1,"garage":"CENTER","type":"bus","lastLocID":2626,"messageCode":268,"time":1395773363828,"expires":1395773781000,"signMessageLong":"14  Hawthorne to Portland","extraBlockID":null,"locationInScheduleDay":42540,"longitude":-122.623213,"blockID":1401,"offRoute":false,"nextLocID":2624,"vehicleID":2608,"signMessage":"14 To Portland","extraTripID":null,"nextStopSeq":29,"routeNumber":14,"vehicleLoad":"unknown","bearing":270,"lastStopSeq":28,"inCongestion":false,"delay":-21,"latitude":45.5120449},{"tripID":4417333,"serviceDate":1395730800000,"direction":1,"garage":"CENTER","type":"bus","lastLocID":7368,"messageCode":788,"time":1395773375749,"expires":1395773793000,"signMessageLong":"70  12th/NE 33rd Ave to Milwaukie","extraBlockID":null,"locationInScheduleDay":42588,"longitude":-122.6307163,"blockID":7010,"offRoute":false,"nextLocID":7374,"vehicleID":2623,"signMessage":"70 To Milwaukie","extraTripID":null,"nextStopSeq":25,"routeNumber":70,"vehicleLoad":"unknown","bearing":179,"lastStopSeq":24,"inCongestion":false,"delay":15,"latitude":45.5491053},{"tripID":4419239,"serviceDate":1395730800000,"direction":1,"garage":"CENTER","type":"bus","lastLocID":10869,"messageCode":813,"time":1395773360569,"expires":1395773778000,"signMessageLong":"77  Broadway/Halsey to Montgomery Park","extraBlockID":null,"locationInScheduleDay":42491,"longitude":-122.6228831,"blockID":7707,"offRoute":false,"nextLocID":7484,"vehicleID":2653,"signMessage":"77 Montgomry Pk","extraTripID":null,"nextStopSeq":69,"routeNumber":77,"vehicleLoad":"unknown","bearing":0,"lastStopSeq":68,"inCongestion":false,"delay":-67,"latitude":45.5342874},{"tripID":4417180,"serviceDate":1395730800000,"direction":0,"garage":"CENTER","type":"bus","lastLocID":4050,"messageCode":783,"time":1395773360576,"expires":1395773780000,"signMessageLong":"70  33rd Ave to NE Sunderland","extraBlockID":null,"locationInScheduleDay":42320,"longitude":-122.6450022,"blockID":7009,"offRoute":false,"nextLocID":7107,"vehicleID":2626,"signMessage":"70 To Sunderlnd","extraTripID":null,"nextStopSeq":38,"routeNumber":70,"vehicleLoad":"unknown","bearing":90,"lastStopSeq":37,"inCongestion":false,"delay":-240,"latitude":45.5314556},{"tripID":4419238,"serviceDate":1395730800000,"direction":1,"garage":"CENTER","type":"bus","lastLocID":7113,"messageCode":813,"time":1395773363818,"expires":1395773781000,"signMessageLong":"77  Broadway/Halsey to Montgomery Park","extraBlockID":null,"locationInScheduleDay":42187,"longitude":-122.6944768,"blockID":7703,"offRoute":false,"nextLocID":7122,"vehicleID":2630,"signMessage":"77 Montgomry Pk","extraTripID":null,"nextStopSeq":96,"routeNumber":77,"vehicleLoad":"unknown","bearing":358,"lastStopSeq":95,"inCongestion":false,"delay":-374,"latitude":45.5276481},{"tripID":4418222,"serviceDate":1395730800000,"direction":1,"garage":"POWELL","type":"bus","lastLocID":3146,"messageCode":760,"time":1395773387288,"expires":1395773806000,"signMessageLong":"72  Killingsworth/82nd to Clackamas TC","extraBlockID":null,"locationInScheduleDay":42042,"longitude":-122.6009615,"blockID":7237,"offRoute":false,"nextLocID":3148,"vehicleID":3004,"signMessage":"72 Clackamas TC","extraTripID":null,"nextStopSeq":47,"routeNumber":72,"vehicleLoad":"unknown","bearing":90,"lastStopSeq":46,"inCongestion":false,"delay":-544,"latitude":45.5627553},{"tripID":4413807,"serviceDate":1395730800000,"direction":0,"garage":"POWELL","type":"bus","lastLocID":13247,"messageCode":456,"time":1395773378337,"expires":1395773796000,"signMessageLong":"31  Clackamas Town Center","extraBlockID":null,"locationInScheduleDay":42402,"longitude":-122.5683542,"blockID":3136,"offRoute":false,"nextLocID":13248,"vehicleID":3007,"signMessage":"31 To Clackamas Town Ctr","extraTripID":null,"nextStopSeq":25,"routeNumber":31,"vehicleLoad":"unknown","bearing":263,"lastStopSeq":24,"inCongestion":false,"delay":0,"latitude":45.4361349},{"tripID":4417893,"serviceDate":1395730800000,"direction":0,"garage":"POWELL","type":"bus","lastLocID":2227,"messageCode":766,"time":1395773387286,"expires":1395773806000,"signMessageLong":"72  Killingsworth/82nd to Swan Island-Anchor St","extraBlockID":null,"locationInScheduleDay":42175,"longitude":-122.6945903,"blockID":7251,"offRoute":false,"nextLocID":2202,"vehicleID":3003,"signMessage":"72 Swan Island","extraTripID":null,"nextStopSeq":106,"routeNumber":72,"vehicleLoad":"unknown","bearing":161,"lastStopSeq":105,"inCongestion":false,"delay":-411,"latitude":45.5600891},{"tripID":4417900,"serviceDate":1395730800000,"direction":0,"garage":"POWELL","type":"bus","lastLocID":13248,"messageCode":766,"time":1395773360502,"expires":1395773779000,"signMessageLong":"72  Killingsworth/82nd to Swan Island-Anchor St","extraBlockID":null,"locationInScheduleDay":42866,"longitude":-122.5690915,"blockID":7235,"offRoute":false,"nextLocID":12922,"vehicleID":3053,"signMessage":"72 Swan Island","extraTripID":null,"nextStopSeq":2,"routeNumber":72,"vehicleLoad":"unknown","bearing":353,"lastStopSeq":1,"inCongestion":false,"delay":307,"latitude":45.4358819},{"tripID":4418223,"serviceDate":1395730800000,"direction":1,"garage":"POWELL","type":"bus","lastLocID":3199,"messageCode":760,"time":1395773360498,"expires":1395773778000,"signMessageLong":"72  Killingsworth/82nd to Clackamas TC","extraBlockID":null,"locationInScheduleDay":42597,"longitude":-122.6159722,"blockID":7245,"offRoute":false,"nextLocID":3144,"vehicleID":3052,"signMessage":"72 Clackamas TC","extraTripID":null,"nextStopSeq":41,"routeNumber":72,"vehicleLoad":"unknown","bearing":90,"lastStopSeq":40,"inCongestion":false,"delay":39,"latitude":45.5627899},{"tripID":4418225,"serviceDate":1395730800000,"direction":1,"garage":"POWELL","type":"bus","lastLocID":8681,"messageCode":760,"time":1395773318818,"expires":1395773735000,"signMessageLong":"72  Killingsworth/82nd to Clackamas TC","extraBlockID":null,"locationInScheduleDay":42522,"longitude":-122.700784,"blockID":7234,"offRoute":false,"nextLocID":9399,"vehicleID":3054,"signMessage":"72 Clackamas TC","extraTripID":null,"nextStopSeq":3,"routeNumber":72,"vehicleLoad":"unknown","bearing":97,"lastStopSeq":2,"inCongestion":false,"delay":7,"latitude":45.556365},{"tripID":4419241,"serviceDate":1395730800000,"direction":1,"garage":"POWELL","type":"bus","lastLocID":9481,"messageCode":813,"time":1395773387310,"expires":1395773806000,"signMessageLong":"77  Broadway/Halsey to Montgomery Park","extraBlockID":null,"locationInScheduleDay":42586,"longitude":-122.3982117,"blockID":7734,"offRoute":false,"nextLocID":9471,"vehicleID":3046,"signMessage":"77 Montgomry Pk","extraTripID":null,"nextStopSeq":2,"routeNumber":77,"vehicleLoad":"unknown","bearing":85,"lastStopSeq":1,"inCongestion":false,"delay":0,"latitude":45.5443612},{"tripID":4411592,"serviceDate":1395730800000,"direction":1,"garage":"POWELL","type":"bus","lastLocID":1831,"messageCode":268,"time":1395773363659,"expires":1395773782000,"signMessageLong":"14  Hawthorne to Portland","extraBlockID":null,"locationInScheduleDay":42562,"longitude":-122.5662917,"blockID":1439,"offRoute":false,"nextLocID":13236,"vehicleID":3034,"signMessage":"14 To Portland","extraTripID":null,"nextStopSeq":2,"routeNumber":14,"vehicleLoad":"unknown","bearing":291,"lastStopSeq":1,"inCongestion":false,"delay":0,"latitude":45.4791765},{"tripID":4419103,"serviceDate":1395730800000,"direction":0,"garage":"POWELL","type":"bus","lastLocID":8484,"messageCode":809,"time":1395773378348,"expires":1395773796000,"signMessageLong":"77  Broadway/Halsey to Troutdale","extraBlockID":null,"locationInScheduleDay":42576,"longitude":-122.7069049,"blockID":7738,"offRoute":false,"nextLocID":8385,"vehicleID":3035,"signMessage":"77 To Troutdale","extraTripID":null,"nextStopSeq":2,"routeNumber":77,"vehicleLoad":"unknown","bearing":178,"lastStopSeq":1,"inCongestion":false,"delay":0,"latitude":45.5370429}],"queryTime":1395773389539}}
