{"resultSet":{"vehicle":[{"tripID":4418276,"serviceDate":1395730800000,"direction":1,"garage":"POWELL","type":"bus","lastLocID":7996,"messageCode":760,"time":1395799548399,"expires":1395799967000,"signMessageLong":"72  Killingsworth/82nd to Clackamas TC","extraBlockID":null,"locationInScheduleDay":68891,"longitude":-122.5790892,"blockID":7257,"offRoute":false,"nextLocID":7988,"vehicleID":2205,"signMessage":"72 Clackamas TC","extraTripID":null,"nextStopSeq":103,"routeNumber":72,"vehicleLoad":"unknown","bearing":180,"lastStopSeq":102,"inCongestion":false,"delay":144,"latitude":45.458501},{"tripID":4419120,"serviceDate":1395730800000,"direction":0,"garage":"POWELL","type":"bus","lastLocID":2327,"messageCode":809,"time":1395799548424,"expires":1395799967000,"signMessageLong":"77  Broadway/Halsey to Troutdale","extraBlockID":null,"locationInScheduleDay":68780,"longitude":-122.4424,"blockID":7739,"offRoute":false,"nextLocID":2436,"vehicleID":2232,"signMessage":"77 To Troutdale","extraTripID":null,"nextStopSeq":88,"routeNumber":77,"vehicleLoad":"unknown","bearing":83,"lastStopSeq":87,"inCongestion":false,"delay":33,"latitude":45.5338306},{"tripID":4411375,"serviceDate":1395730800000,"direction":0,"garage":"POWELL","type":"bus","lastLocID":2612,"messageCode":266,"time":1395799539694,"expires":1395799957000,"signMessageLong":"14  Hawthorne to 94th & Foster","extraBlockID":null,"locationInScheduleDay":68805,"longitude":-122.6376215,"blockID":1436,"offRoute":false,"nextLocID":2614,"vehicleID":2231,"signMessage":"14 To 94-Foster","extraTripID":null,"nextStopSeq":13,"routeNumber":14,"vehicleLoad":"unknown","bearing":91,"lastStopSeq":12,"inCongestion":false,"delay":68,"latitude":45.5120783},{"tripID":4419122,"serviceDate":1395730800000,"direction":0,"garage":"POWELL","type":"bus","lastLocID":653,"messageCode":809,"time":1395799527340,"expires":1395799945000,"signMessageLong":"77  Broadway/Halsey to Troutdale","extraBlockID":null,"locationInScheduleDay":68703,"longitude":-122.6151162,"blockID":7736,"offRoute":false,"nextLocID":2426,"vehicleID":2221,"signMessage":"77 To Troutdale","extraTripID":null,"nextStopSeq":39,"routeNumber":77,"vehicleLoad":"unknown","bearing":89,"lastStopSeq":38,"inCongestion":false,"delay":-22,"latitude":45.5351305},{"tripID":4418280,"serviceDate":1395730800000,"direction":1,"garage":"POWELL","type":"bus","lastLocID":3169,"messageCode":760,"time":1395799548408,"expires":1395799966000,"signMessageLong":"72  Killingsworth/82nd to Clackamas TC","extraBlockID":null,"locationInScheduleDay":68868,"longitude":-122.680118,"blockID":7259,"offRoute":false,"nextLocID":3173,"vehicleID":2246,"signMessage":"72 Clackamas TC","extraTripID":null,"nextStopSeq":13,"routeNumber":72,"vehicleLoad":"unknown","bearing":90,"lastStopSeq":12,"inCongestion":false,"delay":122,"latitude":45.5626648},{"tripID":4417947,"serviceDate":1395730800000,"direction":0,"garage":"POWELL","type":"bus","lastLocID":3203,"messageCode":766,"time":1395799524702,"expires":1395799942000,"signMessageLong":"72  Killingsworth/82nd to Swan Island-Anchor St","extraBlockID":null,"locationInScheduleDay":68733,"longitude":-122.6129866,"blockID":7248,"offRoute":false,"nextLocID":3201,"vehicleID":2242,"signMessage":"72 Swan Island","extraTripID":null,"nextStopSeq":73,"routeNumber":72,"vehicleLoad":"unknown","bearing":270,"lastStopSeq":72,"inCongestion":false,"delay":11,"latitude":45.5627762},{"tripID":4418275,"serviceDate":1395730800000,"direction":1,"garage":"POWELL","type":"bus","lastLocID":12921,"messageCode":760,"time":1395799548431,"expires":1395799966000,"signMessageLong":"72  Killingsworth/82nd to Clackamas TC","extraBlockID":null,"locationInScheduleDay":68751,"longitude":-122.5712661,"blockID":7252,"offRoute":false,"nextLocID":13247,"vehicleID":2283,"signMessage":"72 Clackamas TC","extraTripID":null,"nextStopSeq":111,"routeNumber":72,"vehicleLoad":"unknown","bearing":91,"lastStopSeq":110,"inCongestion":false,"delay":0,"latitude":45.4372131},{"tripID":4417204,"serviceDate":1395730800000,"direction":0,"garage":"CENTER","type":"bus","lastLocID":4047,"messageCode":783,"time":1395799524616,"expires":1395799943000,"signMessageLong":"70  33rd Ave to NE Sunderland","extraBlockID":null,"locationInScheduleDay":68609,"longitude":-122.6515909,"blockID":7006,"offRoute":false,"nextLocID":4048,"vehicleID":2118,"signMessage":"70 To Sunderlnd","extraTripID":null,"nextStopSeq":36,"routeNumber":70,"vehicleLoad":"unknown","bearing":90,"lastStopSeq":35,"inCongestion":false,"delay":-114,"latitude":45.5314842},{"tripID":4417949,"serviceDate":1395730800000,"direction":0,"garage":"POWELL","type":"bus","lastLocID":7957,"messageCode":766,"time":1395799524653,"expires":1395799943000,"signMessageLong":"72  Killingsworth/82nd to Swan Island-Anchor St","extraBlockID":null,"locationInScheduleDay":68550,"longitude":-122.5786994,"blockID":7238,"offRoute":false,"nextLocID":12755,"vehicleID":2527,"signMessage":"72 Swan Island","extraTripID":null,"nextStopSeq":34,"routeNumber":72,"vehicleLoad":"unknown","bearing":0,"lastStopSeq":33,"inCongestion":false,"delay":-173,"latitude":45.5045549},{"tripID":4419258,"serviceDate":1395730800000,"direction":1,"garage":"CENTER","type":"bus","lastLocID":4043,"messageCode":813,"time":1395799548379,"expires":1395799967000,"signMessageLong":"77  Broadway/Halsey to Montgomery Park","extraBlockID":null,"locationInScheduleDay":68786,"longitude":-122.6604832,"blockID":7708,"offRoute":false,"nextLocID":11492,"vehicleID":2517,"signMessage":"77 Montgomry Pk","extraTripID":null,"nextStopSeq":85,"routeNumber":77,"vehicleLoad":"unknown","bearing":270,"lastStopSeq":84,"inCongestion":false,"delay":39,"latitude":45.5315095},{"tripID":4411631,"serviceDate":1395730800000,"direction":1,"garage":"POWELL","type":"bus","lastLocID":1811,"messageCode":268,"time":1395799524796,"expires":1395799943000,"signMessageLong":"14  Hawthorne to Portland","extraBlockID":null,"locationInScheduleDay":68564,"longitude":-122.5901301,"blockID":1434,"offRoute":false,"nextLocID":1807,"vehicleID":2541,"signMessage":"14 To Portland","extraTripID":null,"nextStopSeq":10,"routeNumber":14,"vehicleLoad":"unknown","bearing":299,"lastStopSeq":9,"inCongestion":false,"delay":-159,"latitude":45.486894},{"tripID":4418278,"serviceDate":1395730800000,"direction":1,"garage":"POWELL","type":"bus","lastLocID":8038,"messageCode":760,"time":1395799539656,"expires":1395799956000,"signMessageLong":"72  Killingsworth/82nd to Clackamas TC","extraBlockID":null,"locationInScheduleDay":68652,"longitude":-122.5786844,"blockID":7239,"offRoute":false,"nextLocID":7934,"vehicleID":2540,"signMessage":"72 Clackamas TC","extraTripID":null,"nextStopSeq":56,"routeNumber":72,"vehicleLoad":"unknown","bearing":180,"lastStopSeq":55,"inCongestion":false,"delay":-84,"latitude":45.5526992},{"tripID":4418279,"serviceDate":1395730800000,"direction":1,"garage":"POWELL","type":"bus","lastLocID":3190,"messageCode":760,"time":1395799548394,"expires":1395799967000,"signMessageLong":"72  Killingsworth/82nd to Clackamas TC","extraBlockID":null,"locationInScheduleDay":68759,"longitude":-122.631429,"blockID":7240,"offRoute":false,"nextLocID":3191,"vehicleID":2533,"signMessage":"72 Clackamas TC","extraTripID":null,"nextStopSeq":36,"routeNumber":72,"vehicleLoad":"unknown","bearing":89,"lastStopSeq":35,"inCongestion":false,"delay":12,"latitude":45.5627207},{"tripID":4418281,"serviceDate":1395730800000,"direction":1,"garage":"POWELL","type":"bus","lastLocID":115,"messageCode":760,"time":1395799513705,"expires":1395799931000,"signMessageLong":"72  Killingsworth/82nd to Clackamas TC","extraBlockID":null,"locationInScheduleDay":68711,"longitude":-122.703865,"blockID":7236,"offRoute":false,"nextLocID":8681,"vehicleID":2552,"signMessage":"72 Clackamas TC","extraTripID":null,"nextStopSeq":2,"routeNumber":72,"vehicleLoad":"unknown","bearing":159,"lastStopSeq":1,"inCongestion":false,"delay":0,"latitude":45.5567629},{"tripID":4417951,"serviceDate":1395730800000,"direction":0,"garage":"POWELL","type":"bus","lastLocID":8017,"messageCode":766,"time":1395799539761,"expires":1395799957000,"signMessageLong":"72  Killingsworth/82nd to Swan Island-Anchor St","extraBlockID":null,"locationInScheduleDay":68737,"longitude":-122.5791056,"blockID":7242,"offRoute":false,"nextLocID":7983,"vehicleID":2548,"signMessage":"72 Swan Island","extraTripID":null,"nextStopSeq":9,"routeNumber":72,"vehicleLoad":"unknown","bearing":0,"lastStopSeq":8,"inCongestion":false,"delay":0,"latitude":45.4567145},{"tripID":4418277,"serviceDate":1395730800000,"direction":1,"garage":"POWELL","type":"bus","lastLocID":7958,"messageCode":760,"time":1395799539759,"expires":1395799957000,"signMessageLong":"72  Killingsworth/82nd to Clackamas TC","extraBlockID":null,"locationInScheduleDay":68676,"longitude":-122.5786978,"blockID":7253,"offRoute":false,"nextLocID":7948,"vehicleID":2318,"signMessage":"72 Clackamas TC","extraTripID":null,"nextStopSeq":80,"routeNumber":72,"vehicleLoad":"unknown","bearing":180,"lastStopSeq":79,"inCongestion":false,"delay":-61,"latitude":45.5050686},{"tripID":4419260,"serviceDate":1395730800000,"direction":1,"garage":"CENTER","type":"bus","lastLocID":2395,"messageCode":813,"time":1395799527332,"expires":1395799945000,"signMessageLong":"77  Broadway/Halsey to Montgomery Park","extraBlockID":null,"locationInScheduleDay":68734,"longitude":-122.4954392,"blockID":7705,"offRoute":false,"nextLocID":13026,"vehicleID":2720,"signMessage":"77 Montgomry Pk","extraTripID":null,"nextStopSeq":27,"routeNumber":77,"vehicleLoad":"unknown","bearing":262,"lastStopSeq":26,"inCongestion":false,"delay":9,"latitude":45.5343144},{"tripID":4411374,"serviceDate":1395730800000,"direction":0,"garage":"CENTER","type":"bus","lastLocID":7666,"messageCode":266,"time":1395799539641,"expires":1395799956000,"signMessageLong":"14  Hawthorne to 94th & Foster","extraBlockID":null,"locationInScheduleDay":68839,"longitude":-122.6113703,"blockID":1404,"offRoute":false,"nextLocID":1792,"vehicleID":2718,"signMessage":"14 To 94-Foster","extraTripID":null,"nextStopSeq":29,"routeNumber":14,"vehicleLoad":"unknown","bearing":180,"lastStopSeq":28,"inCongestion":false,"delay":103,"latitude":45.4991999},{"tripID":4417353,"serviceDate":1395730800000,"direction":1,"garage":"CENTER","type":"bus","lastLocID":6899,"messageCode":789,"time":1395799513582,"expires":1395799931000,"signMessageLong":"70  12th Ave to Milwaukie via 17th & Tacoma","extraBlockID":null,"locationInScheduleDay":68674,"longitude":-122.6480804,"blockID":7007,"offRoute":false,"nextLocID":6857,"vehicleID":2709,"signMessage":"70 To Milw via 17","extraTripID":null,"nextStopSeq":68,"routeNumber":70,"vehicleLoad":"unknown","bearing":175,"lastStopSeq":67,"inCongestion":false,"delay":-37,"latitude":45.4766521},{"tripID":4417203,"serviceDate":1395730800000,"direction":0,"garage":"CENTER","type":"bus","lastLocID":9339,"messageCode":783,"time":1395799539641,"expires":1395799958000,"signMessageLong":"70  33rd Ave to NE Sunderland","extraBlockID":null,"locationInScheduleDay":68863,"longitude":-122.6352569,"blockID":7001,"offRoute":false,"nextLocID":11171,"vehicleID":2704,"signMessage":"70 To Sunderlnd","extraTripID":null,"nextStopSeq":80,"routeNumber":70,"vehicleLoad":"unknown","bearing":337,"lastStopSeq":79,"inCongestion":false,"delay":125,"latitude":45.5947304},{"tripID":4417205,"serviceDate":1395730800000,"direction":0,"garage":"CENTER","type":"bus","lastLocID":6893,"messageCode":780,"time":1395799524620,"expires":1395799943000,"signMessageLong":"70  12th/NE 33rd Ave to NE Sunderland","extraBlockID":null,"locationInScheduleDay":68694,"longitude":-122.6483565,"blockID":7003,"offRoute":false,"nextLocID":6863,"vehicleID":2705,"signMessage":"70 To Sunderlnd","extraTripID":null,"nextStopSeq":22,"routeNumber":70,"vehicleLoad":"unknown","bearing":0,"lastStopSeq":21,"inCongestion":false,"delay":-29,"latitude":45.4898965},{"tripID":4417354,"serviceDate":1395730800000,"direction":1,"garage":"CENTER","type":"bus","lastLocID":7400,"messageCode":788,"time":1395799521399,"expires":1395799939000,"signMessageLong":"70  12th/NE 33rd Ave to Milwaukie","extraBlockID":null,"locationInScheduleDay":68754,"longitude":-122.6307022,"blockID":7004,"offRoute":false,"nextLocID":7386,"vehicleID":2701,"signMessage":"70 To Milwaukie","extraTripID":null,"nextStopSeq":28,"routeNumber":70,"vehicleLoad":"unknown","bearing":179,"lastStopSeq":27,"inCongestion":false,"delay":35,"latitude":45.5419258},{"tripID":4411373,"serviceDate":1395730800000,"direction":0,"garage":"CENTER","type":"bus","lastLocID":1816,"messageCode":266,"time":1395799536594,"expires":1395799955000,"signMessageLong":"14  Hawthorne to 94th & Foster","extraBlockID":null,"locationInScheduleDay":68681,"longitude":-122.580496,"blockID":1403,"offRoute":false,"nextLocID":1819,"vehicleID":2618,"signMessage":"14 To 94-Foster","extraTripID":null,"nextStopSeq":42,"routeNumber":14,"vehicleLoad":"unknown","bearing":118,"lastStopSeq":41,"inCongestion":false,"delay":-54,"latitude":45.4834186},{"tripID":4411630,"serviceDate":1395730800000,"direction":1,"garage":"CENTER","type":"bus","lastLocID":3637,"messageCode":268,"time":1395799542318,"expires":1395799959000,"signMessageLong":"14  Hawthorne to Portland","extraBlockID":null,"locationInScheduleDay":68760,"longitude":-122.6545542,"blockID":1406,"offRoute":false,"nextLocID":3641,"vehicleID":2617,"signMessage":"14 To Portland","extraTripID":null,"nextStopSeq":40,"routeNumber":14,"vehicleLoad":"unknown","bearing":270,"lastStopSeq":39,"inCongestion":false,"delay":21,"latitude":45.5129288},{"tripID":4419121,"serviceDate":1395730800000,"direction":0,"garage":"CENTER","type":"bus","lastLocID":2360,"messageCode":809,"time":1395799539715,"expires":1395799958000,"signMessageLong":"77  Broadway/Halsey to Troutdale","extraBlockID":null,"locationInScheduleDay":68771,"longitude":-122.5409773,"blockID":7706,"offRoute":false,"nextLocID":2364,"vehicleID":2648,"signMessage":"77 To Troutdale","extraTripID":null,"nextStopSeq":61,"routeNumber":77,"vehicleLoad":"unknown","bearing":88,"lastStopSeq":60,"inCongestion":false,"delay":33,"latitude":45.5335449},{"tripID":4419259,"serviceDate":1395730800000,"direction":1,"garage":"CENTER","type":"bus","lastLocID":2425,"messageCode":813,"time":1395799524728,"expires":1395799943000,"signMessageLong":"77  Broadway/Halsey to Montgomery Park","extraBlockID":null,"locationInScheduleDay":68727,"longitude":-122.6136589,"blockID":7707,"offRoute":false,"nextLocID":7571,"vehicleID":2653,"signMessage":"77 Montgomry Pk","extraTripID":null,"nextStopSeq":65,"routeNumber":77,"vehicleLoad":"unknown","bearing":270,"lastStopSeq":64,"inCongestion":false,"delay":4,"latitude":45.5337588},{"tripID":4419257,"serviceDate":1395730800000,"direction":1,"garage":"CENTER","type":"bus","lastLocID":8414,"messageCode":813,"time":1395799513680,"expires":1395799929000,"signMessageLong":"77  Broadway/Halsey to Montgomery Park","extraBlockID":null,"locationInScheduleDay":68590,"longitude":-122.7051049,"blockID":7703,"offRoute":false,"nextLocID":8802,"vehicleID":2630,"signMessage":"77 Montgomry Pk","extraTripID":null,"nextStopSeq":104,"routeNumber":77,"vehicleLoad":"unknown","bearing":268,"lastStopSeq":103,"inCongestion":false,"delay":-119,"latitude":45.5368215},{"tripID":4413825,"serviceDate":1395730800000,"direction":0,"garage":"POWELL","type":"bus","lastLocID":3233,"messageCode":456,"time":1395799521377,"expires":1395799941000,"signMessageLong":"31  Clackamas Town Center","extraBlockID":null,"locationInScheduleDay":68810,"longitude":-122.6102647,"blockID":3136,"offRoute":false,"nextLocID":3245,"vehicleID":3007,"signMessage":"31 To Clackamas Town Ctr","extraTripID":null,"nextStopSeq":11,"routeNumber":31,"vehicleLoad":"unknown","bearing":90,"lastStopSeq":10,"inCongestion":false,"delay":89,"latitude":45.4480014},{"tripID":4417944,"serviceDate":1395730800000,"direction":0,"garage":"POWELL","type":"bus","lastLocID":2161,"messageCode":766,"time":1395799539625,"expires":1395799956000,"signMessageLong":"72  Killingsworth/82nd to Swan Island-Anchor St","extraBlockID":null,"locationInScheduleDay":68565,"longitude":-122.7035074,"blockID":7255,"offRoute":false,"nextLocID":115,"vehicleID":3001,"signMessage":"72 Swan Island","extraTripID":null,"nextStopSeq":108,"routeNumber":72,"vehicleLoad":"unknown","bearing":214,"lastStopSeq":107,"inCongestion":false,"delay":-171,"latitude":45.5574181},{"tripID":4417946,"serviceDate":1395730800000,"direction":0,"garage":"POWELL","type":"bus","lastLocID":10184,"messageCode":766,"time":1395799536499,"expires":1395799954000,"signMessageLong":"72  Killingsworth/82nd to Swan Island-Anchor St","extraBlockID":null,"locationInScheduleDay":68746,"longitude":-122.6612024,"blockID":7251,"offRoute":false,"nextLocID":5890,"vehicleID":3003,"signMessage":"72 Swan Island","extraTripID":null,"nextStopSeq":92,"routeNumber":72,"vehicleLoad":"unknown","bearing":270,"lastStopSeq":91,"inCongestion":false,"delay":12,"latitude":45.5591225},{"tripID":4417950,"serviceDate":1395730800000,"direction":0,"garage":"POWELL","type":"bus","lastLocID":7970,"messageCode":766,"time":1395799524637,"expires":1395799943000,"signMessageLong":"72  Killingsworth/82nd to Swan Island-Anchor St","extraBlockID":null,"locationInScheduleDay":68466,"longitude":-122.5790962,"blockID":7245,"offRoute":false,"nextLocID":7960,"vehicleID":3052,"signMessage":"72 Swan Island","extraTripID":null,"nextStopSeq":18,"routeNumber":72,"vehicleLoad":"unknown","bearing":0,"lastStopSeq":17,"inCongestion":false,"delay":-257,"latitude":45.475565},{"tripID":4417945,"serviceDate":1395730800000,"direction":0,"garage":"POWELL","type":"bus","lastLocID":2202,"messageCode":766,"time":1395799524639,"expires":1395799943000,"signMessageLong":"72  Killingsworth/82nd to Swan Island-Anchor St","extraBlockID":null,"locationInScheduleDay":68915,"longitude":-122.6904021,"blockID":7234,"offRoute":false,"nextLocID":2161,"vehicleID":3054,"signMessage":"72 Swan Island","extraTripID":null,"nextStopSeq":107,"routeNumber":72,"vehicleLoad":"unknown","bearing":267,"lastStopSeq":106,"inCongestion":false,"delay":192,"latitude":45.556093},{"tripID":4419261,"serviceDate":1395730800000,"direction":1,"garage":"POWELL","type":"bus","lastLocID":9481,"messageCode":813,"time":1395799533452,"expires":1395799952000,"signMessageLong":"77  Broadway/Halsey to Montgomery Park","extraBlockID":null,"locationInScheduleDay":68732,"longitude":-122.3982117,"blockID":7734,"offRoute":false,"nextLocID":9471,"vehicleID":3046,"signMessage":"77 Montgomry Pk","extraTripID":null,"nextStopSeq":2,"routeNumber":77,"vehicleLoad":"unknown","bearing":85,"lastStopSeq":1,"inCongestion":false,"delay":0,"latitude":45.5443612},{"tripID":4417948,"serviceDate":1395730800000,"direction":0,"garage":"POWELL","type":"bus","lastLocID":8001,"messageCode":766,"time":1395799539627,"expires":1395799958000,"signMessageLong":"72  Killingsworth/82nd to Swan Island-Anchor St","extraBlockID":null,"locationInScheduleDay":68751,"longitude":-122.5788544,"blockID":7241,"offRoute":false,"nextLocID":8046,"vehicleID":3020,"signMessage":"72 Swan Island","extraTripID":null,"nextStopSeq":54,"routeNumber":72,"vehicleLoad":"unknown","bearing":0,"lastStopSeq":53,"inCongestion":false,"delay":13,"latitude":45.5439381},{"tripID":4419123,"serviceDate":1395730800000,"direction":0,"garage":"POWELL","type":"bus","lastLocID":1612,"messageCode":809,"time":1395799527312,"expires":1395799945000,"signMessageLong":"77  Broadway/Halsey to Troutdale","extraBlockID":null,"locationInScheduleDay":68702,"longitude":-122.6661254,"blockID":7738,"offRoute":false,"nextLocID":11817,"vehicleID":3035,"signMessage":"77 To Troutdale","extraTripID":null,"nextStopSeq":19,"routeNumber":77,"vehicleLoad":"unknown","bearing":306,"lastStopSeq":18,"inCongestion":false,"delay":-23,"latitude":45.5295679},{"tripID":4419256,"serviceDate":1395730800000,"direction":1,"garage":"CENTER","type":"bus","lastLocID":8483,"messageCode":813,"time":1395799527343,"expires":1395799945000,"signMessageLong":"77  Broadway/Halsey to Montgomery Park","extraBlockID":null,"locationInScheduleDay":67603,"longitude":-122.7069345,"blockID":7701,"offRoute":false,"nextLocID":8484,"vehicleID":2013,"signMessage":"77 Montgomry Pk","extraTripID":null,"nextStopSeq":109,"routeNumber":77,"vehicleLoad":"unknown","bearing":178,"lastStopSeq":108,"inCongestion":false,"delay":-102,"latitude":45.5377966}],"queryTime":1395799550950}}
