{"resultSet":{"vehicle":[{"tripID":4419242,"serviceDate":1395730800000,"direction":1,"garage":"POWELL","type":"bus","lastLocID":2455,"messageCode":813,"time":1395777983719,"expires":1395778402000,"signMessageLong":"77  Broadway/Halsey to Montgomery Park","extraBlockID":null,"locationInScheduleDay":46886,"longitude":-122.5827079,"blockID":7736,"offRoute":false,"nextLocID":2453,"vehicleID":2221,"signMessage":"77 Montgomry Pk","extraTripID":null,"nextStopSeq":55,"routeNumber":77,"vehicleLoad":"unknown","bearing":270,"lastStopSeq":54,"inCongestion":false,"delay":-296,"latitude":45.5336111},{"tripID":4411597,"serviceDate":1395730800000,"direction":1,"garage":"POWELL","type":"bus","lastLocID":1831,"messageCode":268,"time":1395777982456,"expires":1395778400000,"signMessageLong":"14  Hawthorne to Portland","extraBlockID":null,"locationInScheduleDay":47180,"longitude":-122.5662917,"blockID":1438,"offRoute":false,"nextLocID":13236,"vehicleID":2220,"signMessage":"14 To Portland","extraTripID":null,"nextStopSeq":2,"routeNumber":14,"vehicleLoad":"unknown","bearing":291,"lastStopSeq":1,"inCongestion":false,"delay":0,"latitude":45.4791765},{"tripID":4418233,"serviceDate":1395730800000,"direction":1,"garage":"POWELL","type":"bus","lastLocID":9403,"messageCode":760,"time":1395777953617,"expires":1395778372000,"signMessageLong":"72  Killingsworth/82nd to Clackamas TC","extraBlockID":null,"locationInScheduleDay":47401,"longitude":-122.6950265,"blockID":7243,"offRoute":false,"nextLocID":3160,"vehicleID":2213,"signMessage":"72 Clackamas TC","extraTripID":null,"nextStopSeq":8,"routeNumber":72,"vehicleLoad":"unknown","bearing":90,"lastStopSeq":7,"inCongestion":false,"delay":249,"latitude":45.5627444},{"tripID":4411593,"serviceDate":1395730800000,"direction":1,"garage":"POWELL","type":"bus","lastLocID":13169,"messageCode":266,"time":1395777950899,"expires":1395778370000,"signMessageLong":"14  Hawthorne to 94th & Foster","extraBlockID":null,"locationInScheduleDay":47120,"longitude":-122.6798638,"blockID":1440,"offRoute":false,"nextLocID":3639,"vehicleID":2265,"signMessage":"14 To 94-Foster","extraTripID":null,"nextStopSeq":45,"routeNumber":14,"vehicleLoad":"unknown","bearing":290,"lastStopSeq":44,"inCongestion":false,"delay":-30,"latitude":45.516358},{"tripID":4418226,"serviceDate":1395730800000,"direction":1,"garage":"POWELL","type":"bus","lastLocID":7954,"messageCode":760,"time":1395777992826,"expires":1395778412000,"signMessageLong":"72  Killingsworth/82nd to Clackamas TC","extraBlockID":null,"locationInScheduleDay":47087,"longitude":-122.5790517,"blockID":7139,"offRoute":false,"nextLocID":7945,"vehicleID":2256,"signMessage":"72 Clackamas TC","extraTripID":null,"nextStopSeq":100,"routeNumber":72,"vehicleLoad":"unknown","bearing":179,"lastStopSeq":99,"inCongestion":false,"delay":-105,"latitude":45.4635578},{"tripID":4413893,"serviceDate":1395730800000,"direction":1,"garage":"POWELL","type":"bus","lastLocID":12922,"messageCode":458,"time":1395777996031,"expires":1395778415000,"signMessageLong":"31  To Milwaukie","extraBlockID":null,"locationInScheduleDay":47179,"longitude":-122.578928,"blockID":3137,"offRoute":false,"nextLocID":7941,"vehicleID":2258,"signMessage":"31 To Milwaukie","extraTripID":null,"nextStopSeq":2,"routeNumber":31,"vehicleLoad":"unknown","bearing":0,"lastStopSeq":1,"inCongestion":false,"delay":-16,"latitude":45.4407137},{"tripID":4417899,"serviceDate":1395730800000,"direction":0,"garage":"POWELL","type":"bus","lastLocID":2161,"messageCode":766,"time":1395777950897,"expires":1395778370000,"signMessageLong":"72  Killingsworth/82nd to Swan Island-Anchor St","extraBlockID":null,"locationInScheduleDay":46881,"longitude":-122.7022274,"blockID":7247,"offRoute":false,"nextLocID":115,"vehicleID":2250,"signMessage":"72 Swan Island","extraTripID":null,"nextStopSeq":108,"routeNumber":72,"vehicleLoad":"unknown","bearing":307,"lastStopSeq":107,"inCongestion":false,"delay":0,"latitude":45.5573692},{"tripID":4418231,"serviceDate":1395730800000,"direction":1,"garage":"POWELL","type":"bus","lastLocID":5927,"messageCode":760,"time":1395777953682,"expires":1395778371000,"signMessageLong":"72  Killingsworth/82nd to Clackamas TC","extraBlockID":null,"locationInScheduleDay":47023,"longitude":-122.6615574,"blockID":7246,"offRoute":false,"nextLocID":46,"vehicleID":2296,"signMessage":"72 Clackamas TC","extraTripID":null,"nextStopSeq":21,"routeNumber":72,"vehicleLoad":"unknown","bearing":180,"lastStopSeq":20,"inCongestion":false,"delay":-128,"latitude":45.5596948},{"tripID":4417903,"serviceDate":1395730800000,"direction":0,"garage":"POWELL","type":"bus","lastLocID":7987,"messageCode":768,"time":1395777998832,"expires":1395778417000,"signMessageLong":"72  Killingsworth/82nd to Swan Island-Shipyards","extraBlockID":null,"locationInScheduleDay":47222,"longitude":-122.5790395,"blockID":7252,"offRoute":false,"nextLocID":8010,"vehicleID":2283,"signMessage":"72 Swan Island","extraTripID":null,"nextStopSeq":47,"routeNumber":72,"vehicleLoad":"unknown","bearing":0,"lastStopSeq":46,"inCongestion":false,"delay":25,"latitude":45.5309464},{"tripID":4417902,"serviceDate":1395730800000,"direction":0,"garage":"POWELL","type":"bus","lastLocID":7927,"messageCode":766,"time":1395777996052,"expires":1395778413000,"signMessageLong":"72  Killingsworth/82nd to Swan Island-Anchor St","extraBlockID":null,"locationInScheduleDay":47152,"longitude":-122.578514,"blockID":7244,"offRoute":false,"nextLocID":3216,"vehicleID":2276,"signMessage":"72 Swan Island","extraTripID":null,"nextStopSeq":62,"routeNumber":72,"vehicleLoad":"unknown","bearing":0,"lastStopSeq":61,"inCongestion":false,"delay":-41,"latitude":45.5621495},{"tripID":4417186,"serviceDate":1395730800000,"direction":0,"garage":"CENTER","type":"bus","lastLocID":13477,"messageCode":781,"time":1395777983676,"expires":1395778402000,"signMessageLong":"70  12th/NE 33rd Ave to NE Sunderland via 17th & Tacoma","extraBlockID":null,"locationInScheduleDay":47182,"longitude":-122.6407309,"blockID":7008,"offRoute":false,"nextLocID":8225,"vehicleID":2506,"signMessage":"70 To Sunderland via 17th","extraTripID":null,"nextStopSeq":2,"routeNumber":70,"vehicleLoad":"unknown","bearing":81,"lastStopSeq":1,"inCongestion":false,"delay":0,"latitude":45.4448667},{"tripID":4418230,"serviceDate":1395730800000,"direction":1,"garage":"POWELL","type":"bus","lastLocID":3146,"messageCode":760,"time":1395777968674,"expires":1395778386000,"signMessageLong":"72  Killingsworth/82nd to Clackamas TC","extraBlockID":null,"locationInScheduleDay":47213,"longitude":-122.599955,"blockID":7238,"offRoute":false,"nextLocID":3148,"vehicleID":2527,"signMessage":"72 Clackamas TC","extraTripID":null,"nextStopSeq":47,"routeNumber":72,"vehicleLoad":"unknown","bearing":90,"lastStopSeq":46,"inCongestion":false,"delay":47,"latitude":45.5627544},{"tripID":4417338,"serviceDate":1395730800000,"direction":1,"garage":"CENTER","type":"bus","lastLocID":9368,"messageCode":788,"time":1395778007470,"expires":1395778427000,"signMessageLong":"70  12th/NE 33rd Ave to Milwaukie","extraBlockID":null,"locationInScheduleDay":47207,"longitude":-122.6357648,"blockID":7002,"offRoute":false,"nextLocID":9414,"vehicleID":2524,"signMessage":"70 To Milwaukie","extraTripID":null,"nextStopSeq":2,"routeNumber":70,"vehicleLoad":"unknown","bearing":180,"lastStopSeq":1,"inCongestion":false,"delay":0,"latitude":45.5898735},{"tripID":4411337,"serviceDate":1395730800000,"direction":0,"garage":"POWELL","type":"bus","lastLocID":1812,"messageCode":266,"time":1395778007538,"expires":1395778427000,"signMessageLong":"14  Hawthorne to 94th & Foster","extraBlockID":null,"locationInScheduleDay":47316,"longitude":-122.5845475,"blockID":1434,"offRoute":false,"nextLocID":1814,"vehicleID":2541,"signMessage":"14 To 94-Foster","extraTripID":null,"nextStopSeq":40,"routeNumber":14,"vehicleLoad":"unknown","bearing":115,"lastStopSeq":39,"inCongestion":false,"delay":109,"latitude":45.4849344},{"tripID":4418224,"serviceDate":1395730800000,"direction":1,"garage":"POWELL","type":"bus","lastLocID":12921,"messageCode":760,"time":1395777860687,"expires":1395778279000,"signMessageLong":"72  Killingsworth/82nd to Clackamas TC","extraBlockID":null,"locationInScheduleDay":46609,"longitude":-122.5685864,"blockID":7239,"offRoute":false,"nextLocID":13247,"vehicleID":2540,"signMessage":"72 Clackamas TC","extraTripID":null,"nextStopSeq":111,"routeNumber":72,"vehicleLoad":"unknown","bearing":61,"lastStopSeq":110,"inCongestion":false,"delay":0,"latitude":45.4355586},{"tripID":4418234,"serviceDate":1395730800000,"direction":1,"garage":"POWELL","type":"bus","lastLocID":115,"messageCode":760,"time":1395777995996,"expires":1395778413000,"signMessageLong":"72  Killingsworth/82nd to Clackamas TC","extraBlockID":null,"locationInScheduleDay":47193,"longitude":-122.703865,"blockID":7240,"offRoute":false,"nextLocID":8681,"vehicleID":2533,"signMessage":"72 Clackamas TC","extraTripID":null,"nextStopSeq":2,"routeNumber":72,"vehicleLoad":"unknown","bearing":159,"lastStopSeq":1,"inCongestion":false,"delay":0,"latitude":45.5567629},{"tripID":4418229,"serviceDate":1395730800000,"direction":1,"garage":"POWELL","type":"bus","lastLocID":8038,"messageCode":760,"time":1395777992901,"expires":1395778412000,"signMessageLong":"72  Killingsworth/82nd to Clackamas TC","extraBlockID":null,"locationInScheduleDay":46964,"longitude":-122.5786844,"blockID":7236,"offRoute":false,"nextLocID":7934,"vehicleID":2552,"signMessage":"72 Clackamas TC","extraTripID":null,"nextStopSeq":56,"routeNumber":72,"vehicleLoad":"unknown","bearing":180,"lastStopSeq":55,"inCongestion":false,"delay":-228,"latitude":45.5526992},{"tripID":4413809,"serviceDate":1395730800000,"direction":0,"garage":"POWELL","type":"bus","lastLocID":13247,"messageCode":456,"time":1395777951005,"expires":1395778370000,"signMessageLong":"31  Clackamas Town Center","extraBlockID":null,"locationInScheduleDay":46002,"longitude":-122.5683542,"blockID":3134,"offRoute":false,"nextLocID":13248,"vehicleID":2555,"signMessage":"31 To Clackamas Town Ctr","extraTripID":null,"nextStopSeq":25,"routeNumber":31,"vehicleLoad":"unknown","bearing":263,"lastStopSeq":24,"inCongestion":false,"delay":0,"latitude":45.4361349},{"tripID":4417901,"serviceDate":1395730800000,"direction":0,"garage":"POWELL","type":"bus","lastLocID":64,"messageCode":766,"time":1395777957667,"expires":1395778374000,"signMessageLong":"72  Killingsworth/82nd to Swan Island-Anchor St","extraBlockID":null,"locationInScheduleDay":47107,"longitude":-122.6400486,"blockID":7242,"offRoute":false,"nextLocID":61,"vehicleID":2548,"signMessage":"72 Swan Island","extraTripID":null,"nextStopSeq":84,"routeNumber":72,"vehicleLoad":"unknown","bearing":270,"lastStopSeq":83,"inCongestion":false,"delay":-47,"latitude":45.5590628},{"tripID":4418228,"serviceDate":1395730800000,"direction":1,"garage":"POWELL","type":"bus","lastLocID":8048,"messageCode":760,"time":1395777998851,"expires":1395778417000,"signMessageLong":"72  Killingsworth/82nd to Clackamas TC","extraBlockID":null,"locationInScheduleDay":47056,"longitude":-122.5790811,"blockID":7253,"offRoute":false,"nextLocID":7929,"vehicleID":2318,"signMessage":"72 Clackamas TC","extraTripID":null,"nextStopSeq":73,"routeNumber":72,"vehicleLoad":"unknown","bearing":179,"lastStopSeq":72,"inCongestion":false,"delay":-141,"latitude":45.5192953},{"tripID":4411594,"serviceDate":1395730800000,"direction":1,"garage":"POWELL","type":"bus","lastLocID":2619,"messageCode":268,"time":1395777998863,"expires":1395778416000,"signMessageLong":"14  Hawthorne to Portland","extraBlockID":null,"locationInScheduleDay":47134,"longitude":-122.6324191,"blockID":1435,"offRoute":false,"nextLocID":2616,"vehicleID":2316,"signMessage":"14 To Portland","extraTripID":null,"nextStopSeq":32,"routeNumber":14,"vehicleLoad":"unknown","bearing":270,"lastStopSeq":31,"inCongestion":false,"delay":-62,"latitude":45.5120625},{"tripID":4419240,"serviceDate":1395730800000,"direction":1,"garage":"CENTER","type":"bus","lastLocID":8483,"messageCode":813,"time":1395777983692,"expires":1395778402000,"signMessageLong":"77  Broadway/Halsey to Montgomery Park","extraBlockID":null,"locationInScheduleDay":46422,"longitude":-122.7069345,"blockID":7705,"offRoute":false,"nextLocID":8484,"vehicleID":2720,"signMessage":"77 Montgomry Pk","extraTripID":null,"nextStopSeq":109,"routeNumber":77,"vehicleLoad":"unknown","bearing":178,"lastStopSeq":108,"inCongestion":false,"delay":0,"latitude":45.5377966},{"tripID":4411595,"serviceDate":1395730800000,"direction":1,"garage":"CENTER","type":"bus","lastLocID":1811,"messageCode":268,"time":1395777950838,"expires":1395778370000,"signMessageLong":"14  Hawthorne to Portland","extraBlockID":null,"locationInScheduleDay":46975,"longitude":-122.5897531,"blockID":1404,"offRoute":false,"nextLocID":1807,"vehicleID":2718,"signMessage":"14 To Portland","extraTripID":null,"nextStopSeq":10,"routeNumber":14,"vehicleLoad":"unknown","bearing":299,"lastStopSeq":9,"inCongestion":false,"delay":-175,"latitude":45.486742},{"tripID":4417337,"serviceDate":1395730800000,"direction":1,"garage":"CENTER","type":"bus","lastLocID":7370,"messageCode":788,"time":1395777998645,"expires":1395778416000,"signMessageLong":"70  12th/NE 33rd Ave to Milwaukie","extraBlockID":null,"locationInScheduleDay":47049,"longitude":-122.6306662,"blockID":7007,"offRoute":false,"nextLocID":7388,"vehicleID":2709,"signMessage":"70 To Milwaukie","extraTripID":null,"nextStopSeq":14,"routeNumber":70,"vehicleLoad":"unknown","bearing":179,"lastStopSeq":13,"inCongestion":false,"delay":-147,"latitude":45.5715003},{"tripID":4417184,"serviceDate":1395730800000,"direction":0,"garage":"CENTER","type":"bus","lastLocID":7138,"messageCode":783,"time":1395778007448,"expires":1395778427000,"signMessageLong":"70  33rd Ave to NE Sunderland","extraBlockID":null,"locationInScheduleDay":47189,"longitude":-122.6448414,"blockID":7001,"offRoute":false,"nextLocID":6237,"vehicleID":2704,"signMessage":"70 To Sunderlnd","extraTripID":null,"nextStopSeq":40,"routeNumber":70,"vehicleLoad":"unknown","bearing":359,"lastStopSeq":39,"inCongestion":false,"delay":-18,"latitude":45.5342166},{"tripID":4417335,"serviceDate":1395730800000,"direction":1,"garage":"CENTER","type":"bus","lastLocID":6874,"messageCode":791,"time":1395777998638,"expires":1395778416000,"signMessageLong":"70  To Milwaukie","extraBlockID":null,"locationInScheduleDay":47355,"longitude":-122.6470577,"blockID":7003,"offRoute":false,"nextLocID":6896,"vehicleID":2705,"signMessage":"70 To Milwaukie","extraTripID":null,"nextStopSeq":72,"routeNumber":70,"vehicleLoad":"unknown","bearing":179,"lastStopSeq":71,"inCongestion":false,"delay":159,"latitude":45.4667758},{"tripID":4417183,"serviceDate":1395730800000,"direction":0,"garage":"CENTER","type":"bus","lastLocID":9339,"messageCode":783,"time":1395777957289,"expires":1395778374000,"signMessageLong":"70  33rd Ave to NE Sunderland","extraBlockID":null,"locationInScheduleDay":47250,"longitude":-122.6345513,"blockID":7004,"offRoute":false,"nextLocID":11171,"vehicleID":2701,"signMessage":"70 To Sunderlnd","extraTripID":null,"nextStopSeq":80,"routeNumber":70,"vehicleLoad":"unknown","bearing":336,"lastStopSeq":79,"inCongestion":false,"delay":96,"latitude":45.5935964},{"tripID":4419243,"serviceDate":1395730800000,"direction":1,"garage":"CENTER","type":"bus","lastLocID":2331,"messageCode":813,"time":1395777935801,"expires":1395778354000,"signMessageLong":"77  Broadway/Halsey to Montgomery Park","extraBlockID":null,"locationInScheduleDay":47118,"longitude":-122.4234321,"blockID":7704,"offRoute":false,"nextLocID":2419,"vehicleID":2614,"signMessage":"77 Montgomry Pk","extraTripID":null,"nextStopSeq":11,"routeNumber":77,"vehicleLoad":"unknown","bearing":258,"lastStopSeq":10,"inCongestion":false,"delay":-16,"latitude":45.5364699},{"tripID":4411596,"serviceDate":1395730800000,"direction":1,"garage":"CENTER","type":"bus","lastLocID":1831,"messageCode":268,"time":1395777998837,"expires":1395778418000,"signMessageLong":"14  Hawthorne to Portland","extraBlockID":null,"locationInScheduleDay":47198,"longitude":-122.5662917,"blockID":1401,"offRoute":false,"nextLocID":13236,"vehicleID":2608,"signMessage":"14 To Portland","extraTripID":null,"nextStopSeq":2,"routeNumber":14,"vehicleLoad":"unknown","bearing":291,"lastStopSeq":1,"inCongestion":false,"delay":0,"latitude":45.4791765},{"tripID":4417185,"serviceDate":1395730800000,"direction":0,"garage":"CENTER","type":"bus","lastLocID":4539,"messageCode":780,"time":1395777998807,"expires":1395778417000,"signMessageLong":"70  12th/NE 33rd Ave to NE Sunderland","extraBlockID":null,"locationInScheduleDay":47322,"longitude":-122.6540706,"blockID":7010,"offRoute":false,"nextLocID":6578,"vehicleID":2623,"signMessage":"70 To Sunderlnd","extraTripID":null,"nextStopSeq":27,"routeNumber":70,"vehicleLoad":"unknown","bearing":321,"lastStopSeq":26,"inCongestion":false,"delay":125,"latitude":45.5013665},{"tripID":4419105,"serviceDate":1395730800000,"direction":0,"garage":"CENTER","type":"bus","lastLocID":1611,"messageCode":809,"time":1395777998806,"expires":1395778418000,"signMessageLong":"77  Broadway/Halsey to Troutdale","extraBlockID":null,"locationInScheduleDay":46901,"longitude":-122.6873556,"blockID":7707,"offRoute":false,"nextLocID":1608,"vehicleID":2653,"signMessage":"77 To Troutdale","extraTripID":null,"nextStopSeq":13,"routeNumber":77,"vehicleLoad":"unknown","bearing":91,"lastStopSeq":12,"inCongestion":false,"delay":-297,"latitude":45.5250124},{"tripID":4417336,"serviceDate":1395730800000,"direction":1,"garage":"CENTER","type":"bus","lastLocID":8937,"messageCode":790,"time":1395777998815,"expires":1395778416000,"signMessageLong":"70  12th Ave to Milwaukie via 13th & Tacoma","extraBlockID":null,"locationInScheduleDay":47057,"longitude":-122.6535925,"blockID":7009,"offRoute":false,"nextLocID":6583,"vehicleID":2626,"signMessage":"70 To Milw via 13","extraTripID":null,"nextStopSeq":45,"routeNumber":70,"vehicleLoad":"unknown","bearing":180,"lastStopSeq":44,"inCongestion":false,"delay":-139,"latitude":45.5289317},{"tripID":4419104,"serviceDate":1395730800000,"direction":0,"garage":"CENTER","type":"bus","lastLocID":653,"messageCode":809,"time":1395777996053,"expires":1395778415000,"signMessageLong":"77  Broadway/Halsey to Troutdale","extraBlockID":null,"locationInScheduleDay":46824,"longitude":-122.6151162,"blockID":7703,"offRoute":false,"nextLocID":2426,"vehicleID":2630,"signMessage":"77 To Troutdale","extraTripID":null,"nextStopSeq":39,"routeNumber":77,"vehicleLoad":"unknown","bearing":89,"lastStopSeq":38,"inCongestion":false,"delay":-371,"latitude":45.5351305},{"tripID":4417905,"serviceDate":1395730800000,"direction":0,"garage":"POWELL","type":"bus","lastLocID":8015,"messageCode":766,"time":1395777995915,"expires":1395778414000,"signMessageLong":"72  Killingsworth/82nd to Swan Island-Anchor St","extraBlockID":null,"locationInScheduleDay":46980,"longitude":-122.5791068,"blockID":7237,"offRoute":false,"nextLocID":8017,"vehicleID":3004,"signMessage":"72 Swan Island","extraTripID":null,"nextStopSeq":8,"routeNumber":72,"vehicleLoad":"unknown","bearing":358,"lastStopSeq":7,"inCongestion":false,"delay":-214,"latitude":45.4526458},{"tripID":4413810,"serviceDate":1395730800000,"direction":0,"garage":"POWELL","type":"bus","lastLocID":3251,"messageCode":457,"time":1395777998618,"expires":1395778417000,"signMessageLong":"31  Clackamas Town Center, continuing to Estacada","extraBlockID":null,"locationInScheduleDay":47160,"longitude":-122.584682,"blockID":3136,"offRoute":false,"nextLocID":3226,"vehicleID":3007,"signMessage":"31 To Estacada via Clackamas","extraTripID":null,"nextStopSeq":19,"routeNumber":31,"vehicleLoad":"unknown","bearing":90,"lastStopSeq":18,"inCongestion":false,"delay":-37,"latitude":45.4470488},{"tripID":4418227,"serviceDate":1395730800000,"direction":1,"garage":"POWELL","type":"bus","lastLocID":8009,"messageCode":760,"time":1395777980828,"expires":1395778398000,"signMessageLong":"72  Killingsworth/82nd to Clackamas TC","extraBlockID":null,"locationInScheduleDay":47345,"longitude":-122.5789361,"blockID":7251,"offRoute":false,"nextLocID":7965,"vehicleID":3003,"signMessage":"72 Clackamas TC","extraTripID":null,"nextStopSeq":90,"routeNumber":72,"vehicleLoad":"unknown","bearing":180,"lastStopSeq":89,"inCongestion":false,"delay":167,"latitude":45.484916},{"tripID":4417900,"serviceDate":1395730800000,"direction":0,"garage":"POWELL","type":"bus","lastLocID":53,"messageCode":766,"time":1395777995962,"expires":1395778413000,"signMessageLong":"72  Killingsworth/82nd to Swan Island-Anchor St","extraBlockID":null,"locationInScheduleDay":46568,"longitude":-122.6513405,"blockID":7235,"offRoute":false,"nextLocID":51,"vehicleID":3053,"signMessage":"72 Swan Island","extraTripID":null,"nextStopSeq":88,"routeNumber":72,"vehicleLoad":"unknown","bearing":270,"lastStopSeq":87,"inCongestion":false,"delay":-625,"latitude":45.5590994},{"tripID":4417906,"serviceDate":1395730800000,"direction":0,"garage":"POWELL","type":"bus","lastLocID":13248,"messageCode":766,"time":1395777998654,"expires":1395778416000,"signMessageLong":"72  Killingsworth/82nd to Swan Island-Anchor St","extraBlockID":null,"locationInScheduleDay":47184,"longitude":-122.5690815,"blockID":7245,"offRoute":false,"nextLocID":12922,"vehicleID":3052,"signMessage":"72 Swan Island","extraTripID":null,"nextStopSeq":2,"routeNumber":72,"vehicleLoad":"unknown","bearing":353,"lastStopSeq":1,"inCongestion":false,"delay":-12,"latitude":45.4358222},{"tripID":4418225,"serviceDate":1395730800000,"direction":1,"garage":"POWELL","type":"bus","lastLocID":12921,"messageCode":760,"time":1395777947667,"expires":1395778367000,"signMessageLong":"72  Killingsworth/82nd to Clackamas TC","extraBlockID":null,"locationInScheduleDay":47147,"longitude":-122.5714291,"blockID":7234,"offRoute":false,"nextLocID":13247,"vehicleID":3054,"signMessage":"72 Clackamas TC","extraTripID":null,"nextStopSeq":111,"routeNumber":72,"vehicleLoad":"unknown","bearing":91,"lastStopSeq":110,"inCongestion":false,"delay":0,"latitude":45.4372158},{"tripID":4419241,"serviceDate":1395730800000,"direction":1,"garage":"POWELL","type":"bus","lastLocID":11492,"messageCode":813,"time":1395777953564,"expires":1395778372000,"signMessageLong":"77  Broadway/Halsey to Montgomery Park","extraBlockID":null,"locationInScheduleDay":47032,"longitude":-122.6645156,"blockID":7734,"offRoute":false,"nextLocID":2592,"vehicleID":3046,"signMessage":"77 Montgomry Pk","extraTripID":null,"nextStopSeq":86,"routeNumber":77,"vehicleLoad":"unknown","bearing":270,"lastStopSeq":85,"inCongestion":false,"delay":-120,"latitude":45.5307959},{"tripID":4417904,"serviceDate":1395730800000,"direction":0,"garage":"POWELL","type":"bus","lastLocID":8031,"messageCode":766,"time":1395777998635,"expires":1395778417000,"signMessageLong":"72  Killingsworth/82nd to Swan Island-Anchor St","extraBlockID":null,"locationInScheduleDay":47272,"longitude":-122.5787364,"blockID":7241,"offRoute":false,"nextLocID":8023,"vehicleID":3020,"signMessage":"72 Swan Island","extraTripID":null,"nextStopSeq":29,"routeNumber":72,"vehicleLoad":"unknown","bearing":0,"lastStopSeq":28,"inCongestion":false,"delay":75,"latitude":45.4975908},{"tripID":4411338,"serviceDate":1395730800000,"direction":0,"garage":"POWELL","type":"bus","lastLocID":2625,"messageCode":266,"time":1395777998623,"expires":1395778417000,"signMessageLong":"14  Hawthorne to 94th & Foster","extraBlockID":null,"locationInScheduleDay":47280,"longitude":-122.6230796,"blockID":1439,"offRoute":false,"nextLocID":2628,"vehicleID":3034,"signMessage":"14 To 94-Foster","extraTripID":null,"nextStopSeq":19,"routeNumber":14,"vehicleLoad":"unknown","bearing":90,"lastStopSeq":18,"inCongestion":false,"delay":83,"latitude":45.5120448},{"tripID":4419103,"serviceDate":1395730800000,"direction":0,"garage":"POWELL","type":"bus","lastLocID":2353,"messageCode":809,"time":1395777980838,"expires":1395778397000,"signMessageLong":"77  Broadway/Halsey to Troutdale","extraBlockID":null,"locationInScheduleDay":46945,"longitude":-122.4590298,"blockID":7738,"offRoute":false,"nextLocID":2410,"vehicleID":3035,"signMessage":"77 To Troutdale","extraTripID":null,"nextStopSeq":84,"routeNumber":77,"vehicleLoad":"unknown","bearing":89,"lastStopSeq":83,"inCongestion":false,"delay":-232,"latitude":45.5336378}],"queryTime":1395778009708}}
