{"resultSet":{"vehicle":[{"tripID":4411633,"serviceDate":1395730800000,"direction":1,"garage":"POWELL","type":"bus","lastLocID":3637,"messageCode":268,"time":1395804333702,"expires":1395804752000,"signMessageLong":"14  Hawthorne to Portland","extraBlockID":null,"locationInScheduleDay":73440,"longitude":-122.6545542,"blockID":1436,"offRoute":false,"nextLocID":3641,"vehicleID":2231,"signMessage":"14 To Portland","extraTripID":null,"nextStopSeq":40,"routeNumber":14,"vehicleLoad":"unknown","bearing":270,"lastStopSeq":39,"inCongestion":false,"delay":-92,"latitude":45.5129288},{"tripID":4419263,"serviceDate":1395730800000,"direction":1,"garage":"POWELL","type":"bus","lastLocID":2326,"messageCode":813,"time":1395804336801,"expires":1395804754000,"signMessageLong":"77  Broadway/Halsey to Montgomery Park","extraBlockID":null,"locationInScheduleDay":73484,"longitude":-122.4616944,"blockID":7736,"offRoute":false,"nextLocID":2407,"vehicleID":2221,"signMessage":"77 Montgomry Pk","extraTripID":null,"nextStopSeq":20,"routeNumber":77,"vehicleLoad":"unknown","bearing":270,"lastStopSeq":19,"inCongestion":false,"delay":-50,"latitude":45.5336474},{"tripID":4413827,"serviceDate":1395730800000,"direction":0,"garage":"POWELL","type":"bus","lastLocID":13247,"messageCode":456,"time":1395804336812,"expires":1395804755000,"signMessageLong":"31  Clackamas Town Center","extraBlockID":null,"locationInScheduleDay":73181,"longitude":-122.5683028,"blockID":3138,"offRoute":false,"nextLocID":13248,"vehicleID":2257,"signMessage":"31 To Clackamas Town Ctr","extraTripID":null,"nextStopSeq":25,"routeNumber":31,"vehicleLoad":"unknown","bearing":263,"lastStopSeq":24,"inCongestion":false,"delay":0,"latitude":45.4361392},{"tripID":4418284,"serviceDate":1395730800000,"direction":1,"garage":"POWELL","type":"bus","lastLocID":3199,"messageCode":760,"time":1395804336853,"expires":1395804755000,"signMessageLong":"72  Killingsworth/82nd to Clackamas TC","extraBlockID":null,"locationInScheduleDay":73298,"longitude":-122.6176708,"blockID":7248,"offRoute":false,"nextLocID":3144,"vehicleID":2242,"signMessage":"72 Clackamas TC","extraTripID":null,"nextStopSeq":41,"routeNumber":72,"vehicleLoad":"unknown","bearing":90,"lastStopSeq":40,"inCongestion":false,"delay":-237,"latitude":45.5628009},{"tripID":4417953,"serviceDate":1395730800000,"direction":0,"garage":"POWELL","type":"bus","lastLocID":49,"messageCode":766,"time":1395804325004,"expires":1395804743000,"signMessageLong":"72  Killingsworth/82nd to Swan Island-Anchor St","extraBlockID":null,"locationInScheduleDay":73352,"longitude":-122.6561767,"blockID":7252,"offRoute":false,"nextLocID":70,"vehicleID":2283,"signMessage":"72 Swan Island","extraTripID":null,"nextStopSeq":90,"routeNumber":72,"vehicleLoad":"unknown","bearing":270,"lastStopSeq":89,"inCongestion":false,"delay":-171,"latitude":45.5591146},{"tripID":4418285,"serviceDate":1395730800000,"direction":1,"garage":"POWELL","type":"bus","lastLocID":3173,"messageCode":760,"time":1395804336790,"expires":1395804756000,"signMessageLong":"72  Killingsworth/82nd to Clackamas TC","extraBlockID":null,"locationInScheduleDay":73425,"longitude":-122.6771482,"blockID":7238,"offRoute":false,"nextLocID":3153,"vehicleID":2527,"signMessage":"72 Clackamas TC","extraTripID":null,"nextStopSeq":14,"routeNumber":72,"vehicleLoad":"unknown","bearing":89,"lastStopSeq":13,"inCongestion":false,"delay":-111,"latitude":45.5626755},{"tripID":4411377,"serviceDate":1395730800000,"direction":0,"garage":"POWELL","type":"bus","lastLocID":6398,"messageCode":266,"time":1395804321877,"expires":1395804740000,"signMessageLong":"14  Hawthorne to 94th & Foster","extraBlockID":null,"locationInScheduleDay":72694,"longitude":-122.5647045,"blockID":1434,"offRoute":false,"nextLocID":8134,"vehicleID":2541,"signMessage":"14 To 94-Foster","extraTripID":null,"nextStopSeq":48,"routeNumber":14,"vehicleLoad":"unknown","bearing":109,"lastStopSeq":47,"inCongestion":false,"delay":-826,"latitude":45.4779932},{"tripID":4417956,"serviceDate":1395730800000,"direction":0,"garage":"POWELL","type":"bus","lastLocID":8027,"messageCode":766,"time":1395804324940,"expires":1395804742000,"signMessageLong":"72  Killingsworth/82nd to Swan Island-Anchor St","extraBlockID":null,"locationInScheduleDay":73546,"longitude":-122.5789673,"blockID":7239,"offRoute":false,"nextLocID":7964,"vehicleID":2540,"signMessage":"72 Swan Island","extraTripID":null,"nextStopSeq":22,"routeNumber":72,"vehicleLoad":"unknown","bearing":0,"lastStopSeq":21,"inCongestion":false,"delay":24,"latitude":45.482586},{"tripID":4418281,"serviceDate":1395730800000,"direction":1,"garage":"POWELL","type":"bus","lastLocID":7942,"messageCode":760,"time":1395804348785,"expires":1395804767000,"signMessageLong":"72  Killingsworth/82nd to Clackamas TC","extraBlockID":null,"locationInScheduleDay":73277,"longitude":-122.5789639,"blockID":7236,"offRoute":false,"nextLocID":12921,"vehicleID":2552,"signMessage":"72 Clackamas TC","extraTripID":null,"nextStopSeq":110,"routeNumber":72,"vehicleLoad":"unknown","bearing":181,"lastStopSeq":109,"inCongestion":false,"delay":-270,"latitude":45.439159},{"tripID":4418286,"serviceDate":1395730800000,"direction":1,"garage":"POWELL","type":"bus","lastLocID":115,"messageCode":760,"time":1395804336915,"expires":1395804755000,"signMessageLong":"72  Killingsworth/82nd to Clackamas TC","extraBlockID":null,"locationInScheduleDay":73535,"longitude":-122.703865,"blockID":7242,"offRoute":false,"nextLocID":8681,"vehicleID":2548,"signMessage":"72 Clackamas TC","extraTripID":null,"nextStopSeq":2,"routeNumber":72,"vehicleLoad":"unknown","bearing":159,"lastStopSeq":1,"inCongestion":false,"delay":0,"latitude":45.5567629},{"tripID":4417955,"serviceDate":1395730800000,"direction":0,"garage":"POWELL","type":"bus","lastLocID":8010,"messageCode":766,"time":1395804339609,"expires":1395804757000,"signMessageLong":"72  Killingsworth/82nd to Swan Island-Anchor St","extraBlockID":null,"locationInScheduleDay":73537,"longitude":-122.5790374,"blockID":7253,"offRoute":false,"nextLocID":7999,"vehicleID":2318,"signMessage":"72 Swan Island","extraTripID":null,"nextStopSeq":48,"routeNumber":72,"vehicleLoad":"unknown","bearing":0,"lastStopSeq":47,"inCongestion":false,"delay":0,"latitude":45.5325685},{"tripID":4419260,"serviceDate":1395730800000,"direction":1,"garage":"CENTER","type":"bus","lastLocID":8483,"messageCode":813,"time":1395804327558,"expires":1395804746000,"signMessageLong":"77  Broadway/Halsey to Montgomery Park","extraBlockID":null,"locationInScheduleDay":72343,"longitude":-122.7069345,"blockID":7705,"offRoute":false,"nextLocID":8484,"vehicleID":2720,"signMessage":"77 Montgomry Pk","extraTripID":null,"nextStopSeq":109,"routeNumber":77,"vehicleLoad":"unknown","bearing":178,"lastStopSeq":108,"inCongestion":false,"delay":0,"latitude":45.5377966},{"tripID":4417357,"serviceDate":1395730800000,"direction":1,"garage":"CENTER","type":"bus","lastLocID":9368,"messageCode":788,"time":1395804348697,"expires":1395804766000,"signMessageLong":"70  12th/NE 33rd Ave to Milwaukie","extraBlockID":null,"locationInScheduleDay":73546,"longitude":-122.6357648,"blockID":7007,"offRoute":false,"nextLocID":9414,"vehicleID":2709,"signMessage":"70 To Milwaukie","extraTripID":null,"nextStopSeq":2,"routeNumber":70,"vehicleLoad":"unknown","bearing":180,"lastStopSeq":1,"inCongestion":false,"delay":0,"latitude":45.5898735},{"tripID":4417208,"serviceDate":1395730800000,"direction":0,"garage":"CENTER","type":"bus","lastLocID":13477,"messageCode":781,"time":1395804336755,"expires":1395804755000,"signMessageLong":"70  12th/NE 33rd Ave to NE Sunderland via 17th & Tacoma","extraBlockID":null,"locationInScheduleDay":73535,"longitude":-122.6407309,"blockID":7001,"offRoute":false,"nextLocID":8225,"vehicleID":2704,"signMessage":"70 To Sunderland via 17th","extraTripID":null,"nextStopSeq":2,"routeNumber":70,"vehicleLoad":"unknown","bearing":81,"lastStopSeq":1,"inCongestion":false,"delay":0,"latitude":45.4448667},{"tripID":4417356,"serviceDate":1395730800000,"direction":1,"garage":"CENTER","type":"bus","lastLocID":8937,"messageCode":790,"time":1395804249761,"expires":1395804668000,"signMessageLong":"70  12th Ave to Milwaukie via 13th & Tacoma","extraBlockID":null,"locationInScheduleDay":73203,"longitude":-122.6546271,"blockID":7003,"offRoute":false,"nextLocID":6583,"vehicleID":2705,"signMessage":"70 To Milw via 13","extraTripID":null,"nextStopSeq":45,"routeNumber":70,"vehicleLoad":"unknown","bearing":90,"lastStopSeq":44,"inCongestion":false,"delay":-245,"latitude":45.5299988},{"tripID":4417207,"serviceDate":1395730800000,"direction":0,"garage":"CENTER","type":"bus","lastLocID":8513,"messageCode":783,"time":1395804336752,"expires":1395804756000,"signMessageLong":"70  33rd Ave to NE Sunderland","extraBlockID":null,"locationInScheduleDay":73500,"longitude":-122.6545979,"blockID":7004,"offRoute":false,"nextLocID":8938,"vehicleID":2701,"signMessage":"70 To Sunderlnd","extraTripID":null,"nextStopSeq":37,"routeNumber":70,"vehicleLoad":"unknown","bearing":0,"lastStopSeq":36,"inCongestion":false,"delay":-36,"latitude":45.5298956},{"tripID":4413907,"serviceDate":1395730800000,"direction":1,"garage":"CENTER","type":"bus","lastLocID":2574,"messageCode":458,"time":1395804333715,"expires":1395804753000,"signMessageLong":"31  To Milwaukie","extraBlockID":null,"locationInScheduleDay":73559,"longitude":-122.6327524,"blockID":7511,"offRoute":false,"nextLocID":2573,"vehicleID":2621,"signMessage":"31 To Milwaukie","extraTripID":null,"nextStopSeq":20,"routeNumber":31,"vehicleLoad":"unknown","bearing":268,"lastStopSeq":19,"inCongestion":false,"delay":26,"latitude":45.4465222},{"tripID":4411378,"serviceDate":1395730800000,"direction":0,"garage":"CENTER","type":"bus","lastLocID":2625,"messageCode":266,"time":1395804348751,"expires":1395804767000,"signMessageLong":"14  Hawthorne to 94th & Foster","extraBlockID":null,"locationInScheduleDay":73200,"longitude":-122.6230796,"blockID":1403,"offRoute":false,"nextLocID":2628,"vehicleID":2618,"signMessage":"14 To 94-Foster","extraTripID":null,"nextStopSeq":19,"routeNumber":14,"vehicleLoad":"unknown","bearing":90,"lastStopSeq":18,"inCongestion":false,"delay":-347,"latitude":45.5120448},{"tripID":4411634,"serviceDate":1395730800000,"direction":1,"garage":"CENTER","type":"bus","lastLocID":1831,"messageCode":268,"time":1395804342669,"expires":1395804760000,"signMessageLong":"14  Hawthorne to Portland","extraBlockID":null,"locationInScheduleDay":73540,"longitude":-122.5662917,"blockID":1406,"offRoute":false,"nextLocID":13236,"vehicleID":2617,"signMessage":"14 To Portland","extraTripID":null,"nextStopSeq":2,"routeNumber":14,"vehicleLoad":"unknown","bearing":291,"lastStopSeq":1,"inCongestion":false,"delay":0,"latitude":45.4791765},{"tripID":4419262,"serviceDate":1395730800000,"direction":1,"garage":"CENTER","type":"bus","lastLocID":7571,"messageCode":813,"time":1395804342640,"expires":1395804759000,"signMessageLong":"77  Broadway/Halsey to Montgomery Park","extraBlockID":null,"locationInScheduleDay":73445,"longitude":-122.616026,"blockID":7706,"offRoute":false,"nextLocID":650,"vehicleID":2648,"signMessage":"77 Montgomry Pk","extraTripID":null,"nextStopSeq":66,"routeNumber":77,"vehicleLoad":"unknown","bearing":269,"lastStopSeq":65,"inCongestion":false,"delay":-94,"latitude":45.5351263},{"tripID":4419126,"serviceDate":1395730800000,"direction":0,"garage":"CENTER","type":"bus","lastLocID":11817,"messageCode":809,"time":1395804324999,"expires":1395804742000,"signMessageLong":"77  Broadway/Halsey to Troutdale","extraBlockID":null,"locationInScheduleDay":73541,"longitude":-122.6637436,"blockID":7707,"offRoute":false,"nextLocID":13708,"vehicleID":2653,"signMessage":"77 To Troutdale","extraTripID":null,"nextStopSeq":20,"routeNumber":77,"vehicleLoad":"unknown","bearing":84,"lastStopSeq":19,"inCongestion":false,"delay":19,"latitude":45.530802},{"tripID":4419125,"serviceDate":1395730800000,"direction":0,"garage":"CENTER","type":"bus","lastLocID":7999,"messageCode":809,"time":1395804325003,"expires":1395804743000,"signMessageLong":"77  Broadway/Halsey to Troutdale","extraBlockID":null,"locationInScheduleDay":73260,"longitude":-122.578962,"blockID":7703,"offRoute":false,"nextLocID":2456,"vehicleID":2630,"signMessage":"77 To Troutdale","extraTripID":null,"nextStopSeq":53,"routeNumber":77,"vehicleLoad":"unknown","bearing":0,"lastStopSeq":52,"inCongestion":false,"delay":-263,"latitude":45.533614},{"tripID":4417952,"serviceDate":1395730800000,"direction":0,"garage":"POWELL","type":"bus","lastLocID":2161,"messageCode":766,"time":1395803988716,"expires":1395804407000,"signMessageLong":"72  Killingsworth/82nd to Swan Island-Anchor St","extraBlockID":null,"locationInScheduleDay":73367,"longitude":-122.7035539,"blockID":7263,"offRoute":false,"nextLocID":115,"vehicleID":3006,"signMessage":"72 Swan Island","extraTripID":null,"nextStopSeq":108,"routeNumber":72,"vehicleLoad":"unknown","bearing":214,"lastStopSeq":107,"inCongestion":false,"delay":0,"latitude":45.5573705},{"tripID":4417954,"serviceDate":1395730800000,"direction":0,"garage":"POWELL","type":"bus","lastLocID":3205,"messageCode":766,"time":1395804348691,"expires":1395804767000,"signMessageLong":"72  Killingsworth/82nd to Swan Island-Anchor St","extraBlockID":null,"locationInScheduleDay":73616,"longitude":-122.6094254,"blockID":3136,"offRoute":false,"nextLocID":3203,"vehicleID":3007,"signMessage":"72 Swan Island","extraTripID":null,"nextStopSeq":72,"routeNumber":72,"vehicleLoad":"unknown","bearing":270,"lastStopSeq":71,"inCongestion":false,"delay":69,"latitude":45.5627595},{"tripID":4418283,"serviceDate":1395730800000,"direction":1,"garage":"POWELL","type":"bus","lastLocID":8000,"messageCode":760,"time":1395804333611,"expires":1395804753000,"signMessageLong":"72  Killingsworth/82nd to Clackamas TC","extraBlockID":null,"locationInScheduleDay":73418,"longitude":-122.5790395,"blockID":7251,"offRoute":false,"nextLocID":7978,"vehicleID":3003,"signMessage":"72 Clackamas TC","extraTripID":null,"nextStopSeq":66,"routeNumber":72,"vehicleLoad":"unknown","bearing":179,"lastStopSeq":65,"inCongestion":false,"delay":-115,"latitude":45.5311196},{"tripID":4418282,"serviceDate":1395730800000,"direction":1,"garage":"POWELL","type":"bus","lastLocID":8013,"messageCode":760,"time":1395804339455,"expires":1395804758000,"signMessageLong":"72  Killingsworth/82nd to Clackamas TC","extraBlockID":null,"locationInScheduleDay":73597,"longitude":-122.5790593,"blockID":7234,"offRoute":false,"nextLocID":7963,"vehicleID":3054,"signMessage":"72 Clackamas TC","extraTripID":null,"nextStopSeq":97,"routeNumber":72,"vehicleLoad":"unknown","bearing":179,"lastStopSeq":96,"inCongestion":false,"delay":59,"latitude":45.4704144},{"tripID":4419261,"serviceDate":1395730800000,"direction":1,"garage":"POWELL","type":"bus","lastLocID":2046,"messageCode":813,"time":1395804333639,"expires":1395804752000,"signMessageLong":"77  Broadway/Halsey to Montgomery Park","extraBlockID":null,"locationInScheduleDay":73406,"longitude":-122.6868124,"blockID":7734,"offRoute":false,"nextLocID":2062,"vehicleID":3046,"signMessage":"77 Montgomry Pk","extraTripID":null,"nextStopSeq":92,"routeNumber":77,"vehicleLoad":"unknown","bearing":268,"lastStopSeq":91,"inCongestion":false,"delay":-126,"latitude":45.5264393},{"tripID":4419264,"serviceDate":1395730800000,"direction":1,"garage":"CENTER","type":"bus","lastLocID":9481,"messageCode":813,"time":1395804348722,"expires":1395804766000,"signMessageLong":"77  Broadway/Halsey to Montgomery Park","extraBlockID":null,"locationInScheduleDay":73546,"longitude":-122.3982117,"blockID":7701,"offRoute":false,"nextLocID":9471,"vehicleID":2013,"signMessage":"77 Montgomry Pk","extraTripID":null,"nextStopSeq":2,"routeNumber":77,"vehicleLoad":"unknown","bearing":85,"lastStopSeq":1,"inCongestion":false,"delay":0,"latitude":45.5443612}],"queryTime":1395804351140}}
